[
  {
    "message": "🔔 Comunicado oficial de AIME\nPor una minería legal, responsable y al servicio del país.\nConoce el pronunciamiento completo.",
    "created_time": "2026-02-03T14:24:41+0000",
    "full_picture": "https://scontent-atl3-2.xx.fbcdn.net/v/t39.30808-6/626311509_918715774141567_7728644417833360929_n.jpg?stp=dst-jpg_p720x720_tt6&_nc_cat=104&ccb=1-7&_nc_sid=13d280&_nc_eui2=AeEwLLasiFWYfOv1pqsolKThINq2A0iQkrIg2rYDSJCSss5-uFsplwElpt7SubcjbUxHdj0WtJMdLZqltK_Fb9oP&_nc_ohc=fIfpxigsoAIQ7kNvwHBec2l&_nc_oc=AdlKcJexSpW2vfhVB80KCfCqNJIi-Fz9Q_GHuB6FB0yq6M9N8pEey7_RlpAjuuT-eZI&_nc_zt=23&_nc_ht=scontent-atl3-2.xx&edm=AKIiGfEEAAAA&_nc_gid=m-7-d1tlbPvrW7UzcLK_qg&_nc_tpa=Q5bMBQGGKU4BZaQHPltdwUG12GSYdEq-kHDYSanLtTSj2xAFJR7YZK03QMBKHTs-F5pZcuCEWy4zfJjzpQ&oh=00_AfsKRAG5UpkrLZb5Mzc7WDg0bOn-1dYiyDhLtOb4zpcRqg&oe=699F86B7",
    "permalink_url": "https://www.facebook.com/686939690652511/posts/918719287474549",
    "attachments": {
      "data": [
        {
          "description": "🔔 Comunicado oficial de AIME\nPor una minería legal, responsable y al servicio del país.\nConoce el pronunciamiento completo.",
          "media": {
            "image": {
              "height": 1018,
              "src": "https://scontent-atl3-2.xx.fbcdn.net/v/t39.30808-6/626311509_918715774141567_7728644417833360929_n.jpg?stp=dst-jpg_p720x720_tt6&_nc_cat=104&ccb=1-7&_nc_sid=13d280&_nc_eui2=AeEwLLasiFWYfOv1pqsolKThINq2A0iQkrIg2rYDSJCSss5-uFsplwElpt7SubcjbUxHdj0WtJMdLZqltK_Fb9oP&_nc_ohc=fIfpxigsoAIQ7kNvwHBec2l&_nc_oc=AdlKcJexSpW2vfhVB80KCfCqNJIi-Fz9Q_GHuB6FB0yq6M9N8pEey7_RlpAjuuT-eZI&_nc_zt=23&_nc_ht=scontent-atl3-2.xx&edm=AKIiGfEEAAAA&_nc_gid=m-7-d1tlbPvrW7UzcLK_qg&_nc_tpa=Q5bMBQF5dzoJ2I6ekxP9obXxlSzNDE-XPGtGFQ2SJhso20uYgc7ajLHaFW0NMzcCmaHyvmJ8BlVIxt93TA&oh=00_AfuVZzyv0RKMec7clACCZ7DJ3hIqtT7pEBcGNwQrzIzIRQ&oe=699F86B7",
              "width": 720
            }
          },
          "target": {
            "id": "918715767474901",
            "url": "https://www.facebook.com/photo.php?fbid=918715767474901&set=a.247201474626337&type=3"
          },
          "type": "photo",
          "url": "https://www.facebook.com/photo.php?fbid=918715767474901&set=a.247201474626337&type=3"
        }
      ]
    },
    "id": "145812602695267_918719287474549"
  },
  {
    "message": "El 31 de enero de 2026, la Asociación de Ingenieros de Minas del Ecuador (AIME) realizó su primera Asamblea Ordinaria, marcando oficialmente el inicio de la gestión del nuevo Directorio.\n\nEn el marco de esta jornada se desarrolló un Taller de Capacitación en Fortalecimiento Institucional, orientado a consolidar la organización interna y fortalecer la gestión gremial. Durante la Asamblea se aprobó el Plan de Trabajo, la agenda de eventos y se socializó el Orgánico Funcional, instrumentos que guiarán el accionar institucional durante el nuevo período.\n\nAIME invita a sus socios activos, adherentes y a la comunidad técnica a sumarse de manera activa al fortalecimiento del gremio, aportando con conocimiento, experiencia y compromiso en la promoción de una minería responsable, técnica y sostenible en el Ecuador.\n\n🔹 AIME – Ingeniería, técnica y compromiso con el país\n#AIME #IngenieríaDeMinas #SectorMinero #MineríaResponsable #GremioProfesional #EcuadorMinero",
    "created_time": "2026-02-03T14:11:25+0000",
    "full_picture": "https://scontent-atl3-3.xx.fbcdn.net/v/t39.30808-6/625965328_918708954142249_4247405098174051013_n.jpg?stp=dst-jpg_s720x720_tt6&_nc_cat=111&ccb=1-7&_nc_sid=13d280&_nc_eui2=AeEp2UIR12ANgtGfIHPhGdnzcf_TauAuVy1x_9Nq4C5XLX5oVrmaYs3Pwu39GCzJvSOUXmqOPV-9jgIOxWBDy_Gi&_nc_ohc=s4khb5sfY5MQ7kNvwFzXb0J&_nc_oc=Admdt8Xzg58ikerSkfWomYBEr_dz8Jkmc2-H8zzOSoTJNaNVr4-_4ux3be8lhqtLrv8&_nc_zt=23&_nc_ht=scontent-atl3-3.xx&edm=AKIiGfEEAAAA&_nc_gid=m-7-d1tlbPvrW7UzcLK_qg&_nc_tpa=Q5bMBQE6bblO5vbUrzMCtC5LpZnrK1LxmtuCyiiSYdTEVt8REXta1SAW0LFo6m9p_0c5CYVUTnN8Fd0DIw&oh=00_Aft-CT4jl4dPkHeCn5yVYWYPi9DY1osMkN_8ffiQB63iKA&oe=699F8E99",
    "permalink_url": "https://www.facebook.com/686939690652511/posts/918709747475503",
    "attachments": {
      "data": [
        {
          "media": {
            "image": {
              "height": 720,
              "src": "https://scontent-atl3-3.xx.fbcdn.net/v/t39.30808-6/625965328_918708954142249_4247405098174051013_n.jpg?stp=dst-jpg_s720x720_tt6&_nc_cat=111&ccb=1-7&_nc_sid=13d280&_nc_eui2=AeEp2UIR12ANgtGfIHPhGdnzcf_TauAuVy1x_9Nq4C5XLX5oVrmaYs3Pwu39GCzJvSOUXmqOPV-9jgIOxWBDy_Gi&_nc_ohc=s4khb5sfY5MQ7kNvwFzXb0J&_nc_oc=Admdt8Xzg58ikerSkfWomYBEr_dz8Jkmc2-H8zzOSoTJNaNVr4-_4ux3be8lhqtLrv8&_nc_zt=23&_nc_ht=scontent-atl3-3.xx&edm=AKIiGfEEAAAA&_nc_gid=m-7-d1tlbPvrW7UzcLK_qg&_nc_tpa=Q5bMBQHPs4RInCotG8xCtyCL1qm4jWayLoxoI188pt8SUa0mJyT-RJJuBO6eVhiRxNhOa7A9azFlG0QYOA&oh=00_AfvqjqlyiyIMrun4hyq1numKVVer8XGFmtcmpUJdi48OAw&oe=699F8E99",
              "width": 720
            }
          },
          "subattachments": {
            "data": [
              {
                "media": {
                  "image": {
                    "height": 720,
                    "src": "https://scontent-atl3-3.xx.fbcdn.net/v/t39.30808-6/625965328_918708954142249_4247405098174051013_n.jpg?stp=dst-jpg_s720x720_tt6&_nc_cat=111&ccb=1-7&_nc_sid=13d280&_nc_eui2=AeEp2UIR12ANgtGfIHPhGdnzcf_TauAuVy1x_9Nq4C5XLX5oVrmaYs3Pwu39GCzJvSOUXmqOPV-9jgIOxWBDy_Gi&_nc_ohc=s4khb5sfY5MQ7kNvwFzXb0J&_nc_oc=Admdt8Xzg58ikerSkfWomYBEr_dz8Jkmc2-H8zzOSoTJNaNVr4-_4ux3be8lhqtLrv8&_nc_zt=23&_nc_ht=scontent-atl3-3.xx&edm=AKIiGfEEAAAA&_nc_gid=m-7-d1tlbPvrW7UzcLK_qg&_nc_tpa=Q5bMBQHZ5GsHHttxFkMBxFZHOecTwv1fmsAzMgVyyBhBt64B2O7Fvjf8DQnmH0wT3HcamiOb9x0Y1eSKfQ&oh=00_Afu2BLUV3QNHYcv3pkHjFVJ-hW0s7lusmAk5gQifl9qA9w&oe=699F8E99",
                    "width": 720
                  }
                },
                "target": {
                  "id": "918708934142251",
                  "url": "https://www.facebook.com/photo.php?fbid=918708934142251&set=a.247201474626337&type=3"
                },
                "type": "photo",
                "url": "https://www.facebook.com/photo.php?fbid=918708934142251&set=a.247201474626337&type=3"
              },
              {
                "media": {
                  "image": {
                    "height": 720,
                    "src": "https://scontent-atl3-2.xx.fbcdn.net/v/t39.30808-6/627033800_918708937475584_7724158294754425118_n.jpg?stp=dst-jpg_s720x720_tt6&_nc_cat=104&ccb=1-7&_nc_sid=13d280&_nc_eui2=AeEP0DKCXSC3WlZ6WQ73Rt4dFYLnV71rAVgVgudXvWsBWHF5o-P8vVAOVrt_1yTzeGs1_-Txh10vNXr-AQS41cbI&_nc_ohc=2Zy6JipJmUkQ7kNvwH9zEye&_nc_oc=Adni8SBYKNrCZ52lQgUO2ESk6ty9UAOYqSa9k7_Tqh1XgtFiPU4RbACEBRZ7Gcbz1SM&_nc_zt=23&_nc_ht=scontent-atl3-2.xx&edm=AKIiGfEEAAAA&_nc_gid=m-7-d1tlbPvrW7UzcLK_qg&_nc_tpa=Q5bMBQFWoOLrBuhA7KNaZ6cmYJyzwR8Myld8OOJbr9JRe9Si6L_bL4ZCMV072Dt9RaGxrXl_6SxA4Yj1VA&oh=00_AfsEoQ8oRtVVhOHfYWq11lp5vw_hzgjTUzLaeUP2Y6p1NA&oe=699FA0CF",
                    "width": 720
                  }
                },
                "target": {
                  "id": "918708900808921",
                  "url": "https://www.facebook.com/photo.php?fbid=918708900808921&set=a.247201474626337&type=3"
                },
                "type": "photo",
                "url": "https://www.facebook.com/photo.php?fbid=918708900808921&set=a.247201474626337&type=3"
              },
              {
                "media": {
                  "image": {
                    "height": 720,
                    "src": "https://scontent-atl3-1.xx.fbcdn.net/v/t39.30808-6/626071371_918708947475583_3540134503628051263_n.jpg?stp=dst-jpg_s720x720_tt6&_nc_cat=103&ccb=1-7&_nc_sid=13d280&_nc_eui2=AeGgjNMtTs-rbIuoes_DfPchUko4N3MO9u5SSjg3cw727jBGOqVYySudoQVa0Hq42JSIDNkr4XlE7dJJ7kkz1eHZ&_nc_ohc=KRb0wiwrArcQ7kNvwErvKJ4&_nc_oc=AdkuNcGLs9KeMn8XD9oEBfzbTnQ8jJCPQzS0CF3VgXBci7n72jk0EM97hbdttE-xTiw&_nc_zt=23&_nc_ht=scontent-atl3-1.xx&edm=AKIiGfEEAAAA&_nc_gid=m-7-d1tlbPvrW7UzcLK_qg&_nc_tpa=Q5bMBQGyj699f9sTFF_IuipwtDP5FMKIXfT0Wmk5AdBiiobVWcSa3z2DDTYnEf39MHxPx9y9H6QOGfCirg&oh=00_AftAo1Zj5VBerMWbqbxiWVYv9pmCaecZtM5dLadyDWeODg&oe=699F804F",
                    "width": 720
                  }
                },
                "target": {
                  "id": "918708920808919",
                  "url": "https://www.facebook.com/photo.php?fbid=918708920808919&set=a.247201474626337&type=3"
                },
                "type": "photo",
                "url": "https://www.facebook.com/photo.php?fbid=918708920808919&set=a.247201474626337&type=3"
              },
              {
                "media": {
                  "image": {
                    "height": 720,
                    "src": "https://scontent-atl3-3.xx.fbcdn.net/v/t39.30808-6/626426692_918708944142250_1036398075793413657_n.jpg?stp=dst-jpg_s720x720_tt6&_nc_cat=111&ccb=1-7&_nc_sid=13d280&_nc_eui2=AeHVtWWuKqqnZsn3AMNLqywfxMrd_OjreKnEyt386Ot4qZALb3poVG8u6NXq9vGi0425QPW-KWOz3tZcAgfWhl2D&_nc_ohc=3nukyAc_1A8Q7kNvwESQJFi&_nc_oc=AdmkhPFCoTU0qd5TD2fxRgOJub6gv_7SSX0uBGh16_iZcvQzjLb-V5TnV0GCaF6ZSm4&_nc_zt=23&_nc_ht=scontent-atl3-3.xx&edm=AKIiGfEEAAAA&_nc_gid=m-7-d1tlbPvrW7UzcLK_qg&_nc_tpa=Q5bMBQEHpoxQosDH5oa6_y3zVOOUej-nNx4Fy2vyzdinarYEwZqw69409lgnC4f13VwI8XNKroPfaaNZRg&oh=00_AfuDNBlC4Xtg8b4Fa_5lDfQBsAfI17brGTNL35MOkoFz6A&oe=699FA006",
                    "width": 720
                  }
                },
                "target": {
                  "id": "918708910808920",
                  "url": "https://www.facebook.com/photo.php?fbid=918708910808920&set=a.247201474626337&type=3"
                },
                "type": "photo",
                "url": "https://www.facebook.com/photo.php?fbid=918708910808920&set=a.247201474626337&type=3"
              },
              {
                "media": {
                  "image": {
                    "height": 720,
                    "src": "https://scontent-atl3-1.xx.fbcdn.net/v/t39.30808-6/626256792_918708950808916_5910975446171210722_n.jpg?stp=dst-jpg_s720x720_tt6&_nc_cat=103&ccb=1-7&_nc_sid=13d280&_nc_eui2=AeGriU6OdNflkGX5sixEGhGFJRVmnVv537olFWadW_nfuoEIC1OrGxCaaUvruN6ox7DKygUgKTBQ2rgkkvr_lu0L&_nc_ohc=AMhveISMWYgQ7kNvwGAUaIg&_nc_oc=AdnCb2xyj53WNqOonnawNbG4lJ86j_2eFBqJN3iz0d09xaz8Lyd0qLDs7cL53bR2ERI&_nc_zt=23&_nc_ht=scontent-atl3-1.xx&edm=AKIiGfEEAAAA&_nc_gid=m-7-d1tlbPvrW7UzcLK_qg&_nc_tpa=Q5bMBQEw9OaDeKSv98UIYST6VCN4_7ytdVoMd3OMj1EuYq6roGhzuyU2fppNiS0VVzXfs7Z-xYpyq5npxQ&oh=00_AfvF_w-nJZY4XywCWjWEwk8PMSzCEu7LhIqFguda3iHxOA&oe=699F8419",
                    "width": 720
                  }
                },
                "target": {
                  "id": "918708927475585",
                  "url": "https://www.facebook.com/photo.php?fbid=918708927475585&set=a.247201474626337&type=3"
                },
                "type": "photo",
                "url": "https://www.facebook.com/photo.php?fbid=918708927475585&set=a.247201474626337&type=3"
              }
            ]
          },
          "target": {
            "id": "918709747475503",
            "url": "https://www.facebook.com/686939690652511/posts/918709747475503"
          },
          "title": "Fotos de la publicación de AIME Asociación de Ingenieros de Minas del Ecuador",
          "type": "album",
          "url": "https://www.facebook.com/686939690652511/posts/918709747475503"
        }
      ]
    },
    "id": "145812602695267_918709747475503"
  },
  {
    "message": "✨ Bienvenido 2026 ✨\nDesde AIME iniciamos un nuevo año y una nueva gestión con la convicción de que los grandes desafíos se superan con unidad, diálogo y colaboración.\nInvitamos a los sectores gremiales, académicos, productivos y comunitarios a sumarse a este nuevo ciclo, fortaleciendo alianzas y construyendo juntos una agenda común orientada a la innovación, la productividad y el desarrollo sostenible.\n\nQue este 2026 sea un año de trabajo conjunto y resultados compartidos.\n\n¡Feliz Año Nuevo!",
    "created_time": "2026-01-01T23:19:07+0000",
    "full_picture": "https://scontent-atl3-1.xx.fbcdn.net/v/t39.30808-6/610727149_892919310054547_7733623888713264264_n.jpg?stp=dst-jpg_p720x720_tt6&_nc_cat=106&ccb=1-7&_nc_sid=13d280&_nc_eui2=AeGukn9m5hwQOJ2DXDkoYoyJ2nfDWGPjec_ad8NYY-N5z0rm0ki14TQd4oGvU0ji7mZonQjN3FuU_t2HmZxzMNFy&_nc_ohc=GKYiEETaf5kQ7kNvwG-ufFx&_nc_oc=AdlLSWf6ZgJfjkAs7udqFrdM1GHo86iqeHdqAUXzawklsc1Acmj8YwRMbZ5yIC03bGk&_nc_zt=23&_nc_ht=scontent-atl3-1.xx&edm=AKIiGfEEAAAA&_nc_gid=m-7-d1tlbPvrW7UzcLK_qg&_nc_tpa=Q5bMBQF8Zlt1EETo8VNVNpbggZBOt4QcpC9EQ0_yAZw_dUbDFGLHMirogNMXNgvHFMlEOYSn5VlxRyrQHw&oh=00_AfvXvyjEbYh-VrhtzMopsvh95CC_-rRAkRBQIUHRm74-tA&oe=699F92B4",
    "permalink_url": "https://www.facebook.com/686939690652511/posts/892919413387870",
    "attachments": {
      "data": [
        {
          "description": "✨ Bienvenido 2026 ✨\nDesde AIME iniciamos un nuevo año y una nueva gestión con la convicción de que los grandes desafíos se superan con unidad, diálogo y colaboración.\nInvitamos a los sectores gremiales, académicos, productivos y comunitarios a sumarse a este nuevo ciclo, fortaleciendo alianzas y construyendo juntos una agenda común orientada a la innovación, la productividad y el desarrollo sostenible.\n\nQue este 2026 sea un año de trabajo conjunto y resultados compartidos.\n\n¡Feliz Año Nuevo!",
          "media": {
            "image": {
              "height": 1280,
              "src": "https://scontent-atl3-1.xx.fbcdn.net/v/t39.30808-6/610727149_892919310054547_7733623888713264264_n.jpg?stp=dst-jpg_p720x720_tt6&_nc_cat=106&ccb=1-7&_nc_sid=13d280&_nc_eui2=AeGukn9m5hwQOJ2DXDkoYoyJ2nfDWGPjec_ad8NYY-N5z0rm0ki14TQd4oGvU0ji7mZonQjN3FuU_t2HmZxzMNFy&_nc_ohc=GKYiEETaf5kQ7kNvwG-ufFx&_nc_oc=AdlLSWf6ZgJfjkAs7udqFrdM1GHo86iqeHdqAUXzawklsc1Acmj8YwRMbZ5yIC03bGk&_nc_zt=23&_nc_ht=scontent-atl3-1.xx&edm=AKIiGfEEAAAA&_nc_gid=m-7-d1tlbPvrW7UzcLK_qg&_nc_tpa=Q5bMBQFNteaS-NHMPrwUlkID2oBjSlzebyMKwYrep76cFga2fXQXbJBn0fCB8NoulwiScksGDqWOIuGP9Q&oh=00_AfsopKCgq0hpgUXVcTJHAJpY904Sk7ZvwHAclUUaWf5jJw&oe=699F92B4",
              "width": 720
            }
          },
          "target": {
            "id": "892919306721214",
            "url": "https://www.facebook.com/photo.php?fbid=892919306721214&set=a.247201474626337&type=3"
          },
          "type": "photo",
          "url": "https://www.facebook.com/photo.php?fbid=892919306721214&set=a.247201474626337&type=3"
        }
      ]
    },
    "id": "145812602695267_892919413387870"
  },
  {
    "message": "Cerramos el año agradecidos por cada historia y cada esfuerzo compartido 🤍\nQue esta Navidad traiga calma y nuevos comienzos para todos.\nFeliz Navidad 🎄 – AIME",
    "created_time": "2025-12-25T00:45:03+0000",
    "full_picture": "https://scontent-atl3-3.xx.fbcdn.net/v/t15.5256-10/602827323_1206877248207975_3347233117356364028_n.jpg?_nc_cat=108&ccb=1-7&_nc_sid=d2b52d&_nc_eui2=AeHqJ2_5V3tf7X6SCpcryWRPUT4h363BqlpRPiHfrcGqWvFm_Vw1lzc6vgrudexveSHsXTvVmtHGrYAyfR5BCSSb&_nc_ohc=I0YapkZ96vYQ7kNvwGJHxXL&_nc_oc=AdntEmSmTNkSShzavACLdLFwJ1gZG0ID6iipbc-vj45J-wxf6BnsnK9S36y0fKpbXeQ&_nc_zt=23&_nc_ht=scontent-atl3-3.xx&edm=AKIiGfEEAAAA&_nc_gid=m-7-d1tlbPvrW7UzcLK_qg&_nc_tpa=Q5bMBQHmuNuT24JipPNICXo73ak-_16NKcqelnP-GbGpQEs8A8tcQH8pEwdMYKOXhQaOdmQM1z7iat70OQ&oh=00_AftUN75ACnf4eVqkVuJ5DuItm4jUNtTwcP0yTveIJ1R8dw&oe=699F9BBC",
    "permalink_url": "https://www.facebook.com/reel/842536381917630/",
    "attachments": {
      "data": [
        {
          "media": {
            "image": {
              "height": 720,
              "src": "https://scontent-atl3-3.xx.fbcdn.net/v/t15.5256-10/602827323_1206877248207975_3347233117356364028_n.jpg?stp=dst-jpg_s720x720_tt6&_nc_cat=108&ccb=1-7&_nc_sid=d2b52d&_nc_eui2=AeHqJ2_5V3tf7X6SCpcryWRPUT4h363BqlpRPiHfrcGqWvFm_Vw1lzc6vgrudexveSHsXTvVmtHGrYAyfR5BCSSb&_nc_ohc=I0YapkZ96vYQ7kNvwGJHxXL&_nc_oc=AdntEmSmTNkSShzavACLdLFwJ1gZG0ID6iipbc-vj45J-wxf6BnsnK9S36y0fKpbXeQ&_nc_zt=23&_nc_ht=scontent-atl3-3.xx&edm=AKIiGfEEAAAA&_nc_gid=m-7-d1tlbPvrW7UzcLK_qg&_nc_tpa=Q5bMBQHqQDzaNVzpHhsfPuMx-0bd0nb6YQ6OZd6_V2NYgib4cCXegm-rtVEd1GuPq5Q68SuIYDIOJtfrww&oh=00_AfspBTizNnVc0RAdCXJBTX44Y8nbWU3a7f698mS3ZYoKnA&oe=699F9BBC",
              "width": 405
            },
            "source": "https://video-atl3-3.xx.fbcdn.net/o1/v/t2/f2/m366/AQNaO83cbyt-69_e1unhi0EBpMDclxkEeg2bNrGjWgYeveCCBVNZMEj5Ul-ysZa06PUG_ThBEr3pyrielVWX2lUem1h9rhGSgQIrQdVfwFolgw.mp4?_nc_cat=109&_nc_sid=5e9851&_nc_ht=video-atl3-3.xx.fbcdn.net&_nc_ohc=_NjQIWTgP-UQ7kNvwHKlo3e&efg=eyJ2ZW5jb2RlX3RhZyI6Inhwdl9wcm9ncmVzc2l2ZS5GQUNFQk9PSy4uQzMuNzIwLmRhc2hfaDI2NC1iYXNpYy1nZW4yXzcyMHAiLCJ4cHZfYXNzZXRfaWQiOjEyNzQ5NzU3MzEyNzMzNjAsImFzc2V0X2FnZV9kYXlzIjo1OCwidmlfdXNlY2FzZV9pZCI6MTAxMjIsImR1cmF0aW9uX3MiOjEzLCJ1cmxnZW5fc291cmNlIjoid3d3In0%3D&ccb=17-1&vs=3f16f7cfa471a995&_nc_vs=HBkcFQIYRWZiX2VwaGVtZXJhbC80RjQ1NjQzNEVDMzg2NkJDMjk1MTk5MEVCNDUzRjM5Ml9tdF8xX3ZpZGVvX2Rhc2hpbml0Lm1wNBUAAsgBEgAoABgAGwKIB3VzZV9vaWwBMRJwcm9ncmVzc2l2ZV9yZWNpcGUBMRUAACaguvq4reXDBBUCKAJDMywXQCtU_fO2RaIYGWRhc2hfaDI2NC1iYXNpYy1nZW4yXzcyMHARAHUCZZSeAQA&_nc_gid=m-7-d1tlbPvrW7UzcLK_qg&edm=AKIiGfEEAAAA&_nc_zt=28&_nc_eui2=AeFPfNok84adnEF2DfszOXTlhsFwWlSBJI6GwXBaVIEkjhuXHvojHhzcr8GXM4QGcuUr2zlvH-vFWoKQMHI_msI6&_nc_tpa=Q5bMBQE3zNjmAco5IHYWAfadk70CcWA3wO64RSobltA0fHlPyowrkDWDOOFUfTYtYBUucccvEG5f9Q4-KQ&oh=00_Aftzm8wc8sofkdfzQ5TsIGQZ5obYId1h3nb73LMuUDhKpw&oe=699FAA2B&bitrate=0&tag=dash_h264-basic-gen2_720p"
          },
          "target": {
            "id": "842536381917630",
            "url": "https://www.facebook.com/reel/842536381917630/"
          },
          "type": "video_inline",
          "url": "https://www.facebook.com/reel/842536381917630/"
        }
      ]
    },
    "id": "145812602695267_886934773986334"
  },
  {
    "message": "El 22 de diciembre del 2025  la Asociación de Ingenieros de Minas del Ecuador (AIME) realizó su Asamblea General Extraordinaria, en la que se aprobó el informe económico y de gestión del período 2023–2025 y se eligió al nuevo Directorio que liderará la institución en el siguiente período.\n\nEl proceso electoral se desarrolló de forma presencial y virtual, garantizando la participación democrática de los socios a nivel nacional y fortaleciendo los principios de transparencia y rendición de cuentas.\n\nEl nuevo Directorio reafirmó su compromiso con la unidad del gremio, el diálogo técnico y el trabajo conjunto para aportar al desarrollo responsable, sostenible y transparente de la minería en el Ecuador.\n\n🤝 Seguimos trabajando por un sector minero más fuerte y unido.\n\n#AIME #UnidadGremial #MineríaResponsable #IngenierosDeMinas #EcuadorMiner",
    "created_time": "2025-12-23T23:44:51+0000",
    "full_picture": "https://scontent-atl3-2.xx.fbcdn.net/v/t39.30808-6/604823779_886168660729612_8976496357147182628_n.jpg?stp=dst-jpg_s720x720_tt6&_nc_cat=104&ccb=1-7&_nc_sid=13d280&_nc_eui2=AeG2ho6m_5lsCIyw2HPjYFmpuVzCJE_GmYG5XMIkT8aZgYNNv4dNcohSoW5Im-9zQIGW164HCozSMRyJm3aV5QJr&_nc_ohc=sd-iFoaciq0Q7kNvwHkD45E&_nc_oc=Adlxmv4cHKoo_n1zdA0SjdUpcjK9UoKShnWA67eDQx6yLNVrWNoNEQZXLU6woo8A2sg&_nc_zt=23&_nc_ht=scontent-atl3-2.xx&edm=AKIiGfEEAAAA&_nc_gid=m-7-d1tlbPvrW7UzcLK_qg&_nc_tpa=Q5bMBQFHxfiouCSQ0s17-NaTlU4PKKY4KQfRH54uhAKscXs17X6ICABgPk7O1LnfYLt5GLkPWU6pxnpKYg&oh=00_AfupRG5944GEDNKrctN6hSasryueyL6E1Mz0iprPN6iTNw&oe=699F94C5",
    "permalink_url": "https://www.facebook.com/686939690652511/posts/886169687396176",
    "attachments": {
      "data": [
        {
          "media": {
            "image": {
              "height": 720,
              "src": "https://scontent-atl3-2.xx.fbcdn.net/v/t39.30808-6/604823779_886168660729612_8976496357147182628_n.jpg?stp=dst-jpg_s720x720_tt6&_nc_cat=104&ccb=1-7&_nc_sid=13d280&_nc_eui2=AeG2ho6m_5lsCIyw2HPjYFmpuVzCJE_GmYG5XMIkT8aZgYNNv4dNcohSoW5Im-9zQIGW164HCozSMRyJm3aV5QJr&_nc_ohc=sd-iFoaciq0Q7kNvwHkD45E&_nc_oc=Adlxmv4cHKoo_n1zdA0SjdUpcjK9UoKShnWA67eDQx6yLNVrWNoNEQZXLU6woo8A2sg&_nc_zt=23&_nc_ht=scontent-atl3-2.xx&edm=AKIiGfEEAAAA&_nc_gid=m-7-d1tlbPvrW7UzcLK_qg&_nc_tpa=Q5bMBQHAlFmlMkgAz5QO-rHL-JH1BhyYvCWCLnkoSrFmPR_6C7SndGW3BEGk7p-igBw6o7Hlh5hi61bc_w&oh=00_Afu1wMN5JEVcH_Ax_mMB9y627n6daeiY7OQfGW4ks3TdYA&oe=699F94C5",
              "width": 720
            }
          },
          "subattachments": {
            "data": [
              {
                "media": {
                  "image": {
                    "height": 720,
                    "src": "https://scontent-atl3-2.xx.fbcdn.net/v/t39.30808-6/604823779_886168660729612_8976496357147182628_n.jpg?stp=dst-jpg_s720x720_tt6&_nc_cat=104&ccb=1-7&_nc_sid=13d280&_nc_eui2=AeG2ho6m_5lsCIyw2HPjYFmpuVzCJE_GmYG5XMIkT8aZgYNNv4dNcohSoW5Im-9zQIGW164HCozSMRyJm3aV5QJr&_nc_ohc=sd-iFoaciq0Q7kNvwHkD45E&_nc_oc=Adlxmv4cHKoo_n1zdA0SjdUpcjK9UoKShnWA67eDQx6yLNVrWNoNEQZXLU6woo8A2sg&_nc_zt=23&_nc_ht=scontent-atl3-2.xx&edm=AKIiGfEEAAAA&_nc_gid=m-7-d1tlbPvrW7UzcLK_qg&_nc_tpa=Q5bMBQFucDH2ORM7plB0quEQahfSfGXJ9siAsdUH4yaFXioNimN5b2391ogEDppUnPKCWhPsynsP-4SHkA&oh=00_AfuzHSlGG5bWEoC4WKI7Pgao5Ew6upUw0f-4V4DE7K1i9g&oe=699F94C5",
                    "width": 720
                  }
                },
                "target": {
                  "id": "886168654062946",
                  "url": "https://www.facebook.com/photo.php?fbid=886168654062946&set=a.247201474626337&type=3"
                },
                "type": "photo",
                "url": "https://www.facebook.com/photo.php?fbid=886168654062946&set=a.247201474626337&type=3"
              },
              {
                "media": {
                  "image": {
                    "height": 720,
                    "src": "https://scontent-atl3-1.xx.fbcdn.net/v/t39.30808-6/603090460_886169387396206_4248492605034810153_n.jpg?stp=dst-jpg_s720x720_tt6&_nc_cat=103&ccb=1-7&_nc_sid=13d280&_nc_eui2=AeERQT1HEJKXK_ge1WtVW_OdqLPdYzi8Nu2os91jOLw27WP4-nM5Hije2sGlTvdajSdFAUUoz4jwG0M1sAWwb59O&_nc_ohc=sWA-Wfq5qesQ7kNvwFMWSP1&_nc_oc=AdkRqgYqr11VnvwBzCGQ8hzwPviJRxxJ7uJ-EK7uPtxyzqi_MkZ7WDWnXfBvLh93Vbk&_nc_zt=23&_nc_ht=scontent-atl3-1.xx&edm=AKIiGfEEAAAA&_nc_gid=m-7-d1tlbPvrW7UzcLK_qg&_nc_tpa=Q5bMBQHslupntyT5GkTaEOC8KMpQaqllqqnp4kLtMELOGuXJk9EAGQHyZdNE9D21OU11lXmtUNftx1zdlA&oh=00_Afv90XBVE1pgtk73S_zcs7vK10Sz5nSX7kYPiZQ0NQ2LLQ&oe=699F9114",
                    "width": 720
                  }
                },
                "target": {
                  "id": "886169384062873",
                  "url": "https://www.facebook.com/photo.php?fbid=886169384062873&set=a.247201474626337&type=3"
                },
                "type": "photo",
                "url": "https://www.facebook.com/photo.php?fbid=886169384062873&set=a.247201474626337&type=3"
              },
              {
                "media": {
                  "image": {
                    "height": 720,
                    "src": "https://scontent-atl3-3.xx.fbcdn.net/v/t39.30808-6/603850113_886168640729614_4862515241911493009_n.jpg?stp=dst-jpg_s720x720_tt6&_nc_cat=107&ccb=1-7&_nc_sid=13d280&_nc_eui2=AeHHUOpjNWvqnB1sssxAvC_SPxFgsHCnsRE_EWCwcKexERoDULppURm-tzVU4BNoVrPer6JRd9oxx83SnIWlsGCw&_nc_ohc=I4BVcmyhnKMQ7kNvwGswa6r&_nc_oc=AdmE9cjl5pVxc81reXcbbeN45cib-B9zKXCmvDwMD4NaKGI0upiLMwaYhF-D3NIL__c&_nc_zt=23&_nc_ht=scontent-atl3-3.xx&edm=AKIiGfEEAAAA&_nc_gid=m-7-d1tlbPvrW7UzcLK_qg&_nc_tpa=Q5bMBQEa2LHo4FjCZ2rxtxSooywflZzP5F_D8BToLF-TC6Dw7eDFmYbFldX3chcUOnWOnXtEJpgevNjIUg&oh=00_Afv2b0YdnE-4RNIways7s15BEc2vDMbCstlc0GV1n4tAYQ&oe=699FA537",
                    "width": 720
                  }
                },
                "target": {
                  "id": "886168637396281",
                  "url": "https://www.facebook.com/photo.php?fbid=886168637396281&set=a.247201474626337&type=3"
                },
                "type": "photo",
                "url": "https://www.facebook.com/photo.php?fbid=886168637396281&set=a.247201474626337&type=3"
              }
            ]
          },
          "target": {
            "id": "886169687396176",
            "url": "https://www.facebook.com/686939690652511/posts/886169687396176"
          },
          "title": "Fotos de la publicación de AIME Asociación de Ingenieros de Minas del Ecuador",
          "type": "album",
          "url": "https://www.facebook.com/686939690652511/posts/886169687396176"
        }
      ]
    },
    "id": "145812602695267_886169687396176"
  },
  {
    "created_time": "2025-12-23T23:38:12+0000",
    "full_picture": "https://scontent-atl3-3.xx.fbcdn.net/v/t39.30808-6/427796430_402305149115968_2382000359118265941_n.png?_nc_cat=109&ccb=1-7&_nc_sid=2a1932&_nc_eui2=AeE-X_SEmrwPKyTvZycbaEQxjxkXMPk7wYSPGRcw-TvBhFsnikeiCc2ZDblnzPdVG8_MvRuhzh0FSptEaxnoz7RW&_nc_ohc=M7spmtuUmEsQ7kNvwE_GD1U&_nc_oc=AdkmX8kamZK1iViniYgL4f3C58tIdUbpSUmlofBdF0Rkgg54_LXpevvPb48X0gCfleg&_nc_zt=23&_nc_ht=scontent-atl3-3.xx&edm=AKIiGfEEAAAA&_nc_gid=m-7-d1tlbPvrW7UzcLK_qg&_nc_tpa=Q5bMBQESAPzDpXHZ4qWb-LEPQmG1PUmx5a2CTDUnmNwAj-T-G_hKe7FjxnXS0-gJUA81pJv008YUS02Alw&oh=00_Afta38tMspq1UWNuJT7nsufccGUjG8zLR_hmXyGvXHEeiA&oe=699F8386",
    "permalink_url": "https://www.facebook.com/686939690652511/posts/4127585657494690?substory_index=4127585657494690",
    "attachments": {
      "data": [
        {
          "media": {
            "image": {
              "height": 500,
              "src": "https://scontent-atl3-3.xx.fbcdn.net/v/t39.30808-6/427796430_402305149115968_2382000359118265941_n.png?_nc_cat=109&ccb=1-7&_nc_sid=2a1932&_nc_eui2=AeE-X_SEmrwPKyTvZycbaEQxjxkXMPk7wYSPGRcw-TvBhFsnikeiCc2ZDblnzPdVG8_MvRuhzh0FSptEaxnoz7RW&_nc_ohc=M7spmtuUmEsQ7kNvwE_GD1U&_nc_oc=AdkmX8kamZK1iViniYgL4f3C58tIdUbpSUmlofBdF0Rkgg54_LXpevvPb48X0gCfleg&_nc_zt=23&_nc_ht=scontent-atl3-3.xx&edm=AKIiGfEEAAAA&_nc_gid=m-7-d1tlbPvrW7UzcLK_qg&_nc_tpa=Q5bMBQEPMlO2_PY7RZuONnxsJBXoEpb43wYawQBl_YmhkahuIJXZxUg8N-GyUI_IELAM7tn9t9S54uOLiw&oh=00_AfuCgkcQJhFAkvmUAtYpzB3Ic1odOKSX5hMmhv34vOsyXg&oe=699F8386",
              "width": 1500
            }
          },
          "target": {
            "id": "8505350599483302",
            "url": "https://www.facebook.com/AimeEcuador"
          },
          "title": "Foto de portada de AIME Asociación de Ingenieros de Minas del Ecuador",
          "type": "cover_photo",
          "url": "https://www.facebook.com/AimeEcuador"
        }
      ]
    },
    "id": "145812602695267_4127585657494690"
  },
  {
    "message": "AIME impulsa el diálogo y la unión del sector en el Foro Minería 360° 🔷\n\nLa Asociación de Ingenieros de Minas del Ecuador (AIME) llevó a cabo los días 10 y 11 de diciembre, de manera virtual, el Foro Minería 360°, un espacio de encuentro que permitió reunir a profesionales, expertos e instituciones del sector minero, fomentando el diálogo, el intercambio de conocimientos y la unificación de la industria minera.\n\nDurante las dos jornadas se abordaron temas estratégicos como talento humano, innovación, sostenibilidad y los desafíos actuales del sector, reafirmando el compromiso de AIME con el desarrollo responsable y colaborativo de la minería.\n\nDesde AIME, agradecemos a los ponentes, aliados estratégicos y participantes que formaron parte de este foro y contribuyeron a fortalecer una visión compartida para el futuro de la industria minera.\n\n#AIME #ForoMinería360 #IndustriaMinera #MineríaResponsable #UniónDelSector #MineríaSostenible",
    "created_time": "2025-12-13T18:37:15+0000",
    "full_picture": "https://scontent-atl3-3.xx.fbcdn.net/v/t39.30808-6/598825928_878347124845099_5172489534455890655_n.jpg?stp=dst-jpg_s720x720_tt6&_nc_cat=111&ccb=1-7&_nc_sid=13d280&_nc_eui2=AeHMfq1YIvUP7uTqJOz-n5qELCEYB33oqJIsIRgHfeiokiKtTgDfDiC3mCoWjZJD6cWpH4Sk6RvSiWDKIvh_agfB&_nc_ohc=9ssKm3QGz3YQ7kNvwHpf5N7&_nc_oc=AdlJillirk4Vc1dK09BDr9oxrsFQZtzi2akmigLVGptnlklpo0W2xaJOpiY6w6AoGwA&_nc_zt=23&_nc_ht=scontent-atl3-3.xx&edm=AKIiGfEEAAAA&_nc_gid=m-7-d1tlbPvrW7UzcLK_qg&_nc_tpa=Q5bMBQELDdmNVu0R1qvfc4k9HlaZxXyAPe_KBYXgaeOko4icbZLCdBfymL_oeHpPl7LPkAyA_kk6jbvlXA&oh=00_AfuQUQA_5vGaZadLEf-KGUgRaN4ttUIWO3fVyfhYnv6kog&oe=699FA09A",
    "permalink_url": "https://www.facebook.com/686939690652511/posts/878347284845083",
    "attachments": {
      "data": [
        {
          "media": {
            "image": {
              "height": 720,
              "src": "https://scontent-atl3-3.xx.fbcdn.net/v/t39.30808-6/598825928_878347124845099_5172489534455890655_n.jpg?stp=dst-jpg_s720x720_tt6&_nc_cat=111&ccb=1-7&_nc_sid=13d280&_nc_eui2=AeHMfq1YIvUP7uTqJOz-n5qELCEYB33oqJIsIRgHfeiokiKtTgDfDiC3mCoWjZJD6cWpH4Sk6RvSiWDKIvh_agfB&_nc_ohc=9ssKm3QGz3YQ7kNvwHpf5N7&_nc_oc=AdlJillirk4Vc1dK09BDr9oxrsFQZtzi2akmigLVGptnlklpo0W2xaJOpiY6w6AoGwA&_nc_zt=23&_nc_ht=scontent-atl3-3.xx&edm=AKIiGfEEAAAA&_nc_gid=m-7-d1tlbPvrW7UzcLK_qg&_nc_tpa=Q5bMBQFlzavLSONp0IUDyjYl_OWXmHLXQW_U2DYdy0T4jshfTyBL8LmMtJvCrorsHdvBnYmLHAIt9uBh_g&oh=00_Aft97Qb238mGfmypmVphKnTJ-vVjmX9m5lD1D0ZHd7LUJA&oe=699FA09A",
              "width": 720
            }
          },
          "subattachments": {
            "data": [
              {
                "media": {
                  "image": {
                    "height": 720,
                    "src": "https://scontent-atl3-3.xx.fbcdn.net/v/t39.30808-6/598825928_878347124845099_5172489534455890655_n.jpg?stp=dst-jpg_s720x720_tt6&_nc_cat=111&ccb=1-7&_nc_sid=13d280&_nc_eui2=AeHMfq1YIvUP7uTqJOz-n5qELCEYB33oqJIsIRgHfeiokiKtTgDfDiC3mCoWjZJD6cWpH4Sk6RvSiWDKIvh_agfB&_nc_ohc=9ssKm3QGz3YQ7kNvwHpf5N7&_nc_oc=AdlJillirk4Vc1dK09BDr9oxrsFQZtzi2akmigLVGptnlklpo0W2xaJOpiY6w6AoGwA&_nc_zt=23&_nc_ht=scontent-atl3-3.xx&edm=AKIiGfEEAAAA&_nc_gid=m-7-d1tlbPvrW7UzcLK_qg&_nc_tpa=Q5bMBQGhCsUBwEYa0MuuUGK_kkjNQe1lvd4KJji2bCZCem5I_UR8S-4Czz1aCR6AOf1F8SU722cI_STacg&oh=00_AfuRI6xr0DWhAXnPxNKSXSIbQWHxYB1B7sSnAqXEg4mJgg&oe=699FA09A",
                    "width": 720
                  }
                },
                "target": {
                  "id": "878347121511766",
                  "url": "https://www.facebook.com/photo.php?fbid=878347121511766&set=a.247201474626337&type=3"
                },
                "type": "photo",
                "url": "https://www.facebook.com/photo.php?fbid=878347121511766&set=a.247201474626337&type=3"
              },
              {
                "media": {
                  "image": {
                    "height": 720,
                    "src": "https://scontent-atl3-3.xx.fbcdn.net/v/t39.30808-6/597769654_878347108178434_4403398667528705084_n.jpg?stp=dst-jpg_s720x720_tt6&_nc_cat=107&ccb=1-7&_nc_sid=13d280&_nc_eui2=AeEnKHgLkb2FMhGG1vBM184K3ydOdTICiHjfJ051MgKIeIu8MzIzemUm6LGQHidjE_TwuM1nr2Q09APYiRpyrRUr&_nc_ohc=nsSFAD5uS70Q7kNvwHrwX0U&_nc_oc=Adl9A9EbB9_7nAuqSmsEveEO86SL_xgmxq9zWv55-C3A5bpIStTgRXlhiPYJxT6qGEs&_nc_zt=23&_nc_ht=scontent-atl3-3.xx&edm=AKIiGfEEAAAA&_nc_gid=m-7-d1tlbPvrW7UzcLK_qg&_nc_tpa=Q5bMBQFqeVLquxcLztePYE6pw1wOZKbjijicjPmk_bhzUpYRV0Lpnhon-Z4PEbwl5RZEM6UQsmfGlL4n3Q&oh=00_Afv6AlTe3N12Nh2l0LsPC3fnjs5eadgeK0X40m7C4dcI6g&oe=699F77CA",
                    "width": 720
                  }
                },
                "target": {
                  "id": "878347104845101",
                  "url": "https://www.facebook.com/photo.php?fbid=878347104845101&set=a.247201474626337&type=3"
                },
                "type": "photo",
                "url": "https://www.facebook.com/photo.php?fbid=878347104845101&set=a.247201474626337&type=3"
              }
            ]
          },
          "target": {
            "id": "878347284845083",
            "url": "https://www.facebook.com/686939690652511/posts/878347284845083"
          },
          "title": "Fotos de la publicación de AIME Asociación de Ingenieros de Minas del Ecuador",
          "type": "album",
          "url": "https://www.facebook.com/686939690652511/posts/878347284845083"
        }
      ]
    },
    "id": "145812602695267_878347284845083"
  },
  {
    "message": "🔶 Foro Minería 360° – Día 2\nLa conversación continúa con una mirada profunda hacia el futuro del sector minero ecuatoriano.\n\n📅 11 de diciembre de 2025\n🕖 Foro 4 | 19:10 – 20:00\n📌 “Desafíos y Oportunidades para la Unificación del Sector Minero Ecuatoriano”\n\nExpertos de alto nivel compartirán perspectivas clave sobre cómo lograr una visión común que fortalezca la minería responsable, sostenible y con impacto positivo para el país.\n\n🎙️ Con la participación de representantes del sector, especialistas en pequeña minería y voces investigativas que aportan análisis crítico y constructivo.\n\n🤝 Un espacio para debatir, proponer y avanzar hacia una minería más articulada y competitiva.\n\n🔗 Regístrate aquí: https://forms.gle/iXtSkrUUKFMM1Gcf6\n🌐 www.aimecuador.org",
    "created_time": "2025-12-11T19:50:23+0000",
    "full_picture": "https://scontent-atl3-2.xx.fbcdn.net/v/t39.30808-6/596820603_876845401661938_5601763375222861419_n.jpg?stp=dst-jpg_p720x720_tt6&_nc_cat=104&ccb=1-7&_nc_sid=13d280&_nc_eui2=AeE85ZQc6uvhwm0oOo_3-KJEyxKGSncz12nLEoZKdzPXacJoQ8xYbI7t6_dOj3930esCjrq2bLb4nduzHcI3hSF0&_nc_ohc=Zm2QiVBi-swQ7kNvwHF_m3x&_nc_oc=AdkmV8Zlbaz9mQ4J7WP5SuRjfTc0Wk8gPIEBLD8LubBOLsfKncHFQhMtO0zHJgtQR9E&_nc_zt=23&_nc_ht=scontent-atl3-2.xx&edm=AKIiGfEEAAAA&_nc_gid=m-7-d1tlbPvrW7UzcLK_qg&_nc_tpa=Q5bMBQEKbHnKHVyMH7Mg4Ik5eJlVTflvq1x1DKLMIiYVkJe7IpjAxJL3JFGIsvQ6DPH9W9nghMb_SA8xrg&oh=00_Aftjsux_zIJMsaBqi5Fzu7kgF79Ezm48zJz1KC_WE-6Ddg&oe=699FA82A",
    "permalink_url": "https://www.facebook.com/686939690652511/posts/876845718328573",
    "attachments": {
      "data": [
        {
          "description": "🔶 Foro Minería 360° – Día 2\nLa conversación continúa con una mirada profunda hacia el futuro del sector minero ecuatoriano.\n\n📅 11 de diciembre de 2025\n🕖 Foro 4 | 19:10 – 20:00\n📌 “Desafíos y Oportunidades para la Unificación del Sector Minero Ecuatoriano”\n\nExpertos de alto nivel compartirán perspectivas clave sobre cómo lograr una visión común que fortalezca la minería responsable, sostenible y con impacto positivo para el país.\n\n🎙️ Con la participación de representantes del sector, especialistas en pequeña minería y voces investigativas que aportan análisis crítico y constructivo.\n\n🤝 Un espacio para debatir, proponer y avanzar hacia una minería más articulada y competitiva.\n\n🔗 Regístrate aquí: https://forms.gle/iXtSkrUUKFMM1Gcf6\n🌐 www.aimecuador.org",
          "media": {
            "image": {
              "height": 1279,
              "src": "https://scontent-atl3-2.xx.fbcdn.net/v/t39.30808-6/596820603_876845401661938_5601763375222861419_n.jpg?stp=dst-jpg_p720x720_tt6&_nc_cat=104&ccb=1-7&_nc_sid=13d280&_nc_eui2=AeE85ZQc6uvhwm0oOo_3-KJEyxKGSncz12nLEoZKdzPXacJoQ8xYbI7t6_dOj3930esCjrq2bLb4nduzHcI3hSF0&_nc_ohc=Zm2QiVBi-swQ7kNvwHF_m3x&_nc_oc=AdkmV8Zlbaz9mQ4J7WP5SuRjfTc0Wk8gPIEBLD8LubBOLsfKncHFQhMtO0zHJgtQR9E&_nc_zt=23&_nc_ht=scontent-atl3-2.xx&edm=AKIiGfEEAAAA&_nc_gid=m-7-d1tlbPvrW7UzcLK_qg&_nc_tpa=Q5bMBQEIgr4DNPzajW1qJJa-2LISUdD1yvP3wdtdkeJuandNAz7b8kqeCFQJdJTi8cy-QQmCT2v35e8usw&oh=00_AfvW8GwXTqTqWLyXhq0nyokpzQH9QnWUKdRtGy_56tQk6A&oe=699FA82A",
              "width": 720
            }
          },
          "target": {
            "id": "876845398328605",
            "url": "https://www.facebook.com/photo.php?fbid=876845398328605&set=a.247201474626337&type=3"
          },
          "type": "photo",
          "url": "https://www.facebook.com/photo.php?fbid=876845398328605&set=a.247201474626337&type=3"
        }
      ]
    },
    "id": "145812602695267_876845718328573"
  },
  {
    "message": "🔶 ¡Sé parte del Foro Minería 360°!\nEn el Día 2 exploraremos cómo la minería puede convertirse en un motor de emprendimiento local sostenible, impulsando el desarrollo comunitario con responsabilidad social y enfoque en la seguridad.\n\n📅 11 de diciembre de 2025\n🕕 Foro 3 | 18:10 – 19:10\n📌 “La Minería como Impulsora del Emprendimiento Local Sostenible”\n\nCon la participación de destacados especialistas en gestión social, desarrollo económico e inversión, quienes compartirán experiencias y propuestas para fortalecer los territorios a través de iniciativas productivas.\n\n💬 Únete, aprende y conecta con líderes comprometidos con una minería responsable.\n🔗 Regístrate aquí: https://forms.gle/iXtSkrUUKFMM1Gcf6\n🌐 www.aimecuador.org",
    "created_time": "2025-12-11T19:48:35+0000",
    "full_picture": "https://scontent-atl3-3.xx.fbcdn.net/v/t39.30808-6/598403902_876844658328679_3568713397413541610_n.jpg?stp=dst-jpg_p720x720_tt6&_nc_cat=111&ccb=1-7&_nc_sid=13d280&_nc_eui2=AeHWsU-QTm_LEErsd8a8jnFMA89LfMi8p_UDz0t8yLyn9TP7sFSxnYh2zpVvoVaWsmW_CWucl67osGKDxW7j31zI&_nc_ohc=oBN-rSzRJXQQ7kNvwGPe3Qg&_nc_oc=AdnIOZZW7__GJw7VS3EKW11SXUBY0xjg0JL3A1jC7yVn7Tnb5GCcHSsaWJHm_hkvE04&_nc_zt=23&_nc_ht=scontent-atl3-3.xx&edm=AKIiGfEEAAAA&_nc_gid=m-7-d1tlbPvrW7UzcLK_qg&_nc_tpa=Q5bMBQFqN2aqwuW82LDPxfZg_9r5dxVwq6zKrnbtwonsK8tBpIpd5_yNIENc318mHw-eaKybjIrFG-gqYA&oh=00_AfsuXPYk-b0-2kvzfevkl92Ai8Zx6XjqWN1fUbk5-vSSLg&oe=699FA0E9",
    "permalink_url": "https://www.facebook.com/686939690652511/posts/876844701662008",
    "attachments": {
      "data": [
        {
          "description": "🔶 ¡Sé parte del Foro Minería 360°!\nEn el Día 2 exploraremos cómo la minería puede convertirse en un motor de emprendimiento local sostenible, impulsando el desarrollo comunitario con responsabilidad social y enfoque en la seguridad.\n\n📅 11 de diciembre de 2025\n🕕 Foro 3 | 18:10 – 19:10\n📌 “La Minería como Impulsora del Emprendimiento Local Sostenible”\n\nCon la participación de destacados especialistas en gestión social, desarrollo económico e inversión, quienes compartirán experiencias y propuestas para fortalecer los territorios a través de iniciativas productivas.\n\n💬 Únete, aprende y conecta con líderes comprometidos con una minería responsable.\n🔗 Regístrate aquí: https://forms.gle/iXtSkrUUKFMM1Gcf6\n🌐 www.aimecuador.org",
          "media": {
            "image": {
              "height": 1279,
              "src": "https://scontent-atl3-3.xx.fbcdn.net/v/t39.30808-6/598403902_876844658328679_3568713397413541610_n.jpg?stp=dst-jpg_p720x720_tt6&_nc_cat=111&ccb=1-7&_nc_sid=13d280&_nc_eui2=AeHWsU-QTm_LEErsd8a8jnFMA89LfMi8p_UDz0t8yLyn9TP7sFSxnYh2zpVvoVaWsmW_CWucl67osGKDxW7j31zI&_nc_ohc=oBN-rSzRJXQQ7kNvwGPe3Qg&_nc_oc=AdnIOZZW7__GJw7VS3EKW11SXUBY0xjg0JL3A1jC7yVn7Tnb5GCcHSsaWJHm_hkvE04&_nc_zt=23&_nc_ht=scontent-atl3-3.xx&edm=AKIiGfEEAAAA&_nc_gid=m-7-d1tlbPvrW7UzcLK_qg&_nc_tpa=Q5bMBQHDdCgcguZEM9Xt5lv8WTuzOuDDGiBsSE23wIYfQi-qJSigqG0HRPv6TGAxKlf9VjNeNQdn_Wvmww&oh=00_Afvfq9J8RrMbX17TVZA1D49J-xDoFOR0JkLqrr9y7xyGUw&oe=699FA0E9",
              "width": 720
            }
          },
          "target": {
            "id": "876844654995346",
            "url": "https://www.facebook.com/photo.php?fbid=876844654995346&set=a.247201474626337&type=3"
          },
          "type": "photo",
          "url": "https://www.facebook.com/photo.php?fbid=876844654995346&set=a.247201474626337&type=3"
        }
      ]
    },
    "id": "145812602695267_876844701662008"
  },
  {
    "created_time": "2025-12-11T01:41:15+0000",
    "full_picture": "https://scontent-atl3-2.xx.fbcdn.net/v/t39.30808-6/597220567_876244495055362_5714692223311288606_n.jpg?stp=c0.0.503.1006a_dst-jpg_s720x720_tt6&_nc_cat=101&ccb=1-7&_nc_sid=b2e06f&_nc_eui2=AeHMVsTRyE0qhYD8eUbXi8rUSBHVn0j-yD1IEdWfSP7IPQMmO5vJGIRMC_4QXXkgxv9H5Nlb31BfXtYezvQJ9Xs9&_nc_ohc=o6p8ucmugcgQ7kNvwHc_Cyz&_nc_oc=AdmGnPRS5uDbLFkf_X_kr9GA7BRxHcVj85qGLq5znWb5mI1GZnkLbMPo6CnkPJP5bK8&_nc_zt=23&_nc_ht=scontent-atl3-2.xx&edm=AKIiGfEEAAAA&_nc_gid=m-7-d1tlbPvrW7UzcLK_qg&_nc_tpa=Q5bMBQEbLTwPfw5nGXRb92Nltv225-Ms55pIf2zjdvKvaUMePtg55Or72JK-tNoDxMz1yjfxnUF9e0DnUQ&oh=00_Afv07lSxH_Wy6pJW2tzodye8cMur0izEpma5ZL8VxUfMiw&oe=699F7A42",
    "permalink_url": "https://www.facebook.com/events/2091843138299470/",
    "attachments": {
      "data": [
        {
          "description": "11 asistieron · 4 interesados",
          "media": {
            "image": {
              "height": 720,
              "src": "https://scontent-atl3-2.xx.fbcdn.net/v/t39.30808-6/597220567_876244495055362_5714692223311288606_n.jpg?stp=c0.0.503.1006a_dst-jpg_s720x720_tt6&_nc_cat=101&ccb=1-7&_nc_sid=b2e06f&_nc_eui2=AeHMVsTRyE0qhYD8eUbXi8rUSBHVn0j-yD1IEdWfSP7IPQMmO5vJGIRMC_4QXXkgxv9H5Nlb31BfXtYezvQJ9Xs9&_nc_ohc=o6p8ucmugcgQ7kNvwHc_Cyz&_nc_oc=AdmGnPRS5uDbLFkf_X_kr9GA7BRxHcVj85qGLq5znWb5mI1GZnkLbMPo6CnkPJP5bK8&_nc_zt=23&_nc_ht=scontent-atl3-2.xx&edm=AKIiGfEEAAAA&_nc_gid=m-7-d1tlbPvrW7UzcLK_qg&_nc_tpa=Q5bMBQFOeFGUWUkhUK2dhPj1-RP68aVVxETAAVm9bL95WTgsmCz_vM1KuqUs-YGE-IvmZugFdU19sY2KQw&oh=00_AfsLrQDt-_YDae_xWBOxEfVdhph-_1Lp8kTNtUYEh3hTHg&oe=699F7A42",
              "width": 360
            }
          },
          "target": {
            "id": "2091843138299470",
            "url": "https://www.facebook.com/events/2091843138299470/"
          },
          "title": "FORO MINERIA 360° Dia 2",
          "type": "event",
          "url": "https://www.facebook.com/events/2091843138299470/"
        }
      ]
    },
    "id": "145812602695267_2091843138299470"
  },
  {
    "message": "🔹 Foro Minería 360° – Día 1\nPresentamos el Foro 2 del primer día:\n“La Licencia Ambiental: Tecnología e Innovación como Aliados Clave”\n\n📅 10 de diciembre de 2025\n⏰ 19h15 – 20h00\n\nUn espacio donde expertos del sector minero y ambiental compartirán cómo la innovación se ha convertido en una herramienta esencial para fortalecer los procesos de licenciamiento ambiental en el país.\n\n👷‍♂️ Ponentes invitados:\n• Ing. Oswaldo Sandoval – Comisión Técnica de Innovación y Tecnología AIME\n• Ing. Manuel Aguirre – DATAMINE\n• Ing. Alexandra Jami – Asociación de Consultores Ambientales Individuales\n• Ing. Jaime Salazar – Subsecretaría de Calidad Ambiental, MAE\n\n✨ Acompáñanos y descubre cómo la tecnología está transformando la gestión ambiental en la minería ecuatoriana.\n\n🔗 Regístrate aquí: https://forms.gle/iXtSkrUUKFMM1Gcf6\n🌐 www.aimecuador.org",
    "created_time": "2025-12-10T19:00:24+0000",
    "full_picture": "https://scontent-atl3-2.xx.fbcdn.net/v/t39.30808-6/597207157_876051081741370_2784419458342265575_n.jpg?stp=dst-jpg_p720x720_tt6&_nc_cat=102&ccb=1-7&_nc_sid=13d280&_nc_eui2=AeHgvrjuVZpKHgZkQQ821OwxBGlAokTpg6wEaUCiROmDrE57FFltwIhHBAwI4FC98TsQ6PmURTSqAh4gndoxtuxp&_nc_ohc=qk5fXkhVl1IQ7kNvwEEaKtw&_nc_oc=AdlWqxMWFwbutC35xJqw9QAOnqsp0H6cFNXkfG09CHixXW8dTCgY7zvzNjZG0IUN6R0&_nc_zt=23&_nc_ht=scontent-atl3-2.xx&edm=AKIiGfEEAAAA&_nc_gid=m-7-d1tlbPvrW7UzcLK_qg&_nc_tpa=Q5bMBQHxpkTNopdoh5auJN5Cw_JknRhUhGP0aF-5cBYrVZb8csoIyJW-5CvebNGTZkMn4kflFcVxPcr0kg&oh=00_AfvyY2dSWgjkJ_5O3VzbVIWtIAlQVF5KY3azfq-fA3Jbdg&oe=699F7F84",
    "permalink_url": "https://www.facebook.com/686939690652511/posts/876052025074609",
    "attachments": {
      "data": [
        {
          "description": "🔹 Foro Minería 360° – Día 1\nPresentamos el Foro 2 del primer día:\n“La Licencia Ambiental: Tecnología e Innovación como Aliados Clave”\n\n📅 10 de diciembre de 2025\n⏰ 19h15 – 20h00\n\nUn espacio donde expertos del sector minero y ambiental compartirán cómo la innovación se ha convertido en una herramienta esencial para fortalecer los procesos de licenciamiento ambiental en el país.\n\n👷‍♂️ Ponentes invitados:\n• Ing. Oswaldo Sandoval – Comisión Técnica de Innovación y Tecnología AIME\n• Ing. Manuel Aguirre – DATAMINE\n• Ing. Alexandra Jami – Asociación de Consultores Ambientales Individuales\n• Ing. Jaime Salazar – Subsecretaría de Calidad Ambiental, MAE\n\n✨ Acompáñanos y descubre cómo la tecnología está transformando la gestión ambiental en la minería ecuatoriana.\n\n🔗 Regístrate aquí: https://forms.gle/iXtSkrUUKFMM1Gcf6\n🌐 www.aimecuador.org",
          "media": {
            "image": {
              "height": 1279,
              "src": "https://scontent-atl3-2.xx.fbcdn.net/v/t39.30808-6/597207157_876051081741370_2784419458342265575_n.jpg?stp=dst-jpg_p720x720_tt6&_nc_cat=102&ccb=1-7&_nc_sid=13d280&_nc_eui2=AeHgvrjuVZpKHgZkQQ821OwxBGlAokTpg6wEaUCiROmDrE57FFltwIhHBAwI4FC98TsQ6PmURTSqAh4gndoxtuxp&_nc_ohc=qk5fXkhVl1IQ7kNvwEEaKtw&_nc_oc=AdlWqxMWFwbutC35xJqw9QAOnqsp0H6cFNXkfG09CHixXW8dTCgY7zvzNjZG0IUN6R0&_nc_zt=23&_nc_ht=scontent-atl3-2.xx&edm=AKIiGfEEAAAA&_nc_gid=m-7-d1tlbPvrW7UzcLK_qg&_nc_tpa=Q5bMBQEbhmc9QFjwncAlECJuCTWca2oTBP5bgaOdPFrytUWLz2MfFXutS_Z5qElDbQShbFPPbStJFPyt7A&oh=00_Afu2gIrqiSm6DM_qNydVfazAmrQNlrk8rUeu_2k97lVOAw&oe=699F7F84",
              "width": 720
            }
          },
          "target": {
            "id": "876051078408037",
            "url": "https://www.facebook.com/photo.php?fbid=876051078408037&set=a.247201474626337&type=3"
          },
          "type": "photo",
          "url": "https://www.facebook.com/photo.php?fbid=876051078408037&set=a.247201474626337&type=3"
        }
      ]
    },
    "id": "145812602695267_876052025074609"
  },
  {
    "message": "🔸¡Llega el Foro Minería 360°!\nHoy10 de diciembre iniciamos el Día 1 con el Foro Mineria 360º con el tema:“El Talento Minero del Futuro”, un espacio para inspirar, conectar y construir la nueva generación de profesionales del sector.\n\n🌱 Eje central: Educación, talento y gestión ambiental.\n🕑 Horario: 18h10 – 19h10\n\nContaremos con la participación de destacados ponentes que compartirán su visión sobre los desafíos y oportunidades que transformarán la minería en Ecuador.\n\n✨ Sé parte de la conversación que impulsa el futuro del sector minero.\n\n🔗 Regístrate aquí: https://forms.gle/iXtSkrUUKFMM1Gcf6\n\n🌐 www.aimecuador.org",
    "created_time": "2025-12-10T18:51:40+0000",
    "full_picture": "https://scontent-atl3-3.xx.fbcdn.net/v/t39.30808-6/597659836_876046338408511_7335891794876430602_n.jpg?stp=dst-jpg_p720x720_tt6&_nc_cat=107&ccb=1-7&_nc_sid=13d280&_nc_eui2=AeHRSJkSi2czQXg8d0Upmt8gSt1i1G_t10tK3WLUb-3XS9hPGsliAhirz-frReSAN8jRX6l2aBl6S66K2l9BBU5j&_nc_ohc=jmMkm7iwf6cQ7kNvwF_G7Dd&_nc_oc=AdlAo779v7sCQzbBVYSiLD54xZUe8r5fHguW1KLzczv9S3UzgY3bH_mNrstYpjkn7Xs&_nc_zt=23&_nc_ht=scontent-atl3-3.xx&edm=AKIiGfEEAAAA&_nc_gid=m-7-d1tlbPvrW7UzcLK_qg&_nc_tpa=Q5bMBQG_wCp8m1jXD6XRR-6YoQ-16teDVOVnyb6wQrxJ2SoxncneN5eadYoGGhcbEnA5Fk8ohHIv4BbboA&oh=00_Afu2m2CBZEViUp61o9uERYe_8am2VFNShkH9QkNx7HtAOg&oe=699FA494",
    "permalink_url": "https://www.facebook.com/686939690652511/posts/876047148408430",
    "attachments": {
      "data": [
        {
          "description": "🔸¡Llega el Foro Minería 360°!\nHoy10 de diciembre iniciamos el Día 1 con el Foro Mineria 360º con el tema:“El Talento Minero del Futuro”, un espacio para inspirar, conectar y construir la nueva generación de profesionales del sector.\n\n🌱 Eje central: Educación, talento y gestión ambiental.\n🕑 Horario: 18h10 – 19h10\n\nContaremos con la participación de destacados ponentes que compartirán su visión sobre los desafíos y oportunidades que transformarán la minería en Ecuador.\n\n✨ Sé parte de la conversación que impulsa el futuro del sector minero.\n\n🔗 Regístrate aquí: https://forms.gle/iXtSkrUUKFMM1Gcf6\n\n🌐 www.aimecuador.org",
          "media": {
            "image": {
              "height": 1279,
              "src": "https://scontent-atl3-3.xx.fbcdn.net/v/t39.30808-6/597659836_876046338408511_7335891794876430602_n.jpg?stp=dst-jpg_p720x720_tt6&_nc_cat=107&ccb=1-7&_nc_sid=13d280&_nc_eui2=AeHRSJkSi2czQXg8d0Upmt8gSt1i1G_t10tK3WLUb-3XS9hPGsliAhirz-frReSAN8jRX6l2aBl6S66K2l9BBU5j&_nc_ohc=jmMkm7iwf6cQ7kNvwF_G7Dd&_nc_oc=AdlAo779v7sCQzbBVYSiLD54xZUe8r5fHguW1KLzczv9S3UzgY3bH_mNrstYpjkn7Xs&_nc_zt=23&_nc_ht=scontent-atl3-3.xx&edm=AKIiGfEEAAAA&_nc_gid=m-7-d1tlbPvrW7UzcLK_qg&_nc_tpa=Q5bMBQHeQctfkpUBimqkO0DlZUB6YE2PwAhWeFMjuJ02E6YutsGyThEkSS9z_rdqYbIjOFHYzXHbyK_1bQ&oh=00_AftuA8bk78UsvwDq7n5k3xDHjbL2bhiDUVuJmo9r74_b2g&oe=699FA494",
              "width": 720
            }
          },
          "target": {
            "id": "876046335075178",
            "url": "https://www.facebook.com/photo.php?fbid=876046335075178&set=a.247201474626337&type=3"
          },
          "type": "photo",
          "url": "https://www.facebook.com/photo.php?fbid=876046335075178&set=a.247201474626337&type=3"
        }
      ]
    },
    "id": "145812602695267_876047148408430"
  },
  {
    "created_time": "2025-12-10T01:41:42+0000",
    "full_picture": "https://scontent-atl3-1.xx.fbcdn.net/v/t39.30808-6/596786392_875445025135309_8508033657183568428_n.jpg?stp=dst-jpg_p720x720_tt6&_nc_cat=106&ccb=1-7&_nc_sid=13d280&_nc_eui2=AeFSHtIMn5aZiB8nZfxtpCOuoCzL7zohGFKgLMvvOiEYUjLgc2ys9m3ECehMywwQOtcB6PNNg7jS0M3-IjoJ9y3D&_nc_ohc=VIuBhZhrtX8Q7kNvwH5Rmwg&_nc_oc=Adk5d3Buuzo1RFlYSs6koNDRXxFt5_hOLLAMZe5Jwncl_LmRzmx1gTjYYSUAsE1-KS0&_nc_zt=23&_nc_ht=scontent-atl3-1.xx&edm=AKIiGfEEAAAA&_nc_gid=m-7-d1tlbPvrW7UzcLK_qg&_nc_tpa=Q5bMBQHfOtI78qMmYhh7UxqkKYUHvl9orSpksg51C8qIA557jO_Ds_QrXfSulMxCDWwQQSwzIYJI7lhzJw&oh=00_Afs0dl2Str_Cyc3b7ummrIFJE2MnoERh-wjRuqMptk47qg&oe=699F9CD3",
    "permalink_url": "https://www.facebook.com/686939690652511/posts/875446001801878",
    "attachments": {
      "data": [
        {
          "description": "🔶 Foro Minería 360°\nUn espacio donde expertos, instituciones y empresas líderes se unen para dialogar sobre el presente y futuro de la minería responsable en Ecuador. 🌱⛏️\nSé parte de esta jornada de innovación, sostenibilidad y conocimiento.\n\n📅 Organiza: AIME – Asociación de Ingenieros de Minas del Ecuador\n📞 Información: +593 96 820 4060\n🔗 Regístrate aquí: https://forms.gle/iXtSkrUUKFMM1Gcf6\n🌍 www.aimecuador.org",
          "media": {
            "image": {
              "height": 900,
              "src": "https://scontent-atl3-1.xx.fbcdn.net/v/t39.30808-6/596786392_875445025135309_8508033657183568428_n.jpg?stp=dst-jpg_p720x720_tt6&_nc_cat=106&ccb=1-7&_nc_sid=13d280&_nc_eui2=AeFSHtIMn5aZiB8nZfxtpCOuoCzL7zohGFKgLMvvOiEYUjLgc2ys9m3ECehMywwQOtcB6PNNg7jS0M3-IjoJ9y3D&_nc_ohc=VIuBhZhrtX8Q7kNvwH5Rmwg&_nc_oc=Adk5d3Buuzo1RFlYSs6koNDRXxFt5_hOLLAMZe5Jwncl_LmRzmx1gTjYYSUAsE1-KS0&_nc_zt=23&_nc_ht=scontent-atl3-1.xx&edm=AKIiGfEEAAAA&_nc_gid=m-7-d1tlbPvrW7UzcLK_qg&_nc_tpa=Q5bMBQErHvnQh0sdim-OBuQgfvVfOZZj_w1M6gidjEU-hibFhHrBLFux-Zm6ZpsV3InuNPOHN6xMzxTopg&oh=00_AfsGZwhFluzyfvaLrEg0qIHD79tfHM7ws2RmkCX6CWqU6Q&oe=699F9CD3",
              "width": 720
            }
          },
          "target": {
            "id": "875445021801976",
            "url": "https://www.facebook.com/photo.php?fbid=875445021801976&set=a.247201474626337&type=3"
          },
          "type": "photo",
          "url": "https://www.facebook.com/photo.php?fbid=875445021801976&set=a.247201474626337&type=3"
        }
      ]
    },
    "id": "145812602695267_875446001801878"
  },
  {
    "message": "🔶 Foro Minería 360°\nUn espacio donde expertos, instituciones y empresas líderes se unen para dialogar sobre el presente y futuro de la minería responsable en Ecuador. 🌱⛏️\nSé parte de esta jornada de innovación, sostenibilidad y conocimiento.\n\n📅 Organiza: AIME – Asociación de Ingenieros de Minas del Ecuador\n📞 Información: +593 96 820 4060\n🔗 Regístrate aquí: https://forms.gle/iXtSkrUUKFMM1Gcf6\n🌍 www.aimecuador.org",
    "created_time": "2025-12-10T01:41:18+0000",
    "full_picture": "https://scontent-atl3-1.xx.fbcdn.net/v/t39.30808-6/596786392_875445025135309_8508033657183568428_n.jpg?stp=dst-jpg_p720x720_tt6&_nc_cat=106&ccb=1-7&_nc_sid=13d280&_nc_eui2=AeFSHtIMn5aZiB8nZfxtpCOuoCzL7zohGFKgLMvvOiEYUjLgc2ys9m3ECehMywwQOtcB6PNNg7jS0M3-IjoJ9y3D&_nc_ohc=VIuBhZhrtX8Q7kNvwH5Rmwg&_nc_oc=Adk5d3Buuzo1RFlYSs6koNDRXxFt5_hOLLAMZe5Jwncl_LmRzmx1gTjYYSUAsE1-KS0&_nc_zt=23&_nc_ht=scontent-atl3-1.xx&edm=AKIiGfEEAAAA&_nc_gid=m-7-d1tlbPvrW7UzcLK_qg&_nc_tpa=Q5bMBQHfOtI78qMmYhh7UxqkKYUHvl9orSpksg51C8qIA557jO_Ds_QrXfSulMxCDWwQQSwzIYJI7lhzJw&oh=00_Afs0dl2Str_Cyc3b7ummrIFJE2MnoERh-wjRuqMptk47qg&oe=699F9CD3",
    "permalink_url": "https://www.facebook.com/686939690652511/posts/875445775135234",
    "attachments": {
      "data": [
        {
          "description": "🔶 Foro Minería 360°\nUn espacio donde expertos, instituciones y empresas líderes se unen para dialogar sobre el presente y futuro de la minería responsable en Ecuador. 🌱⛏️\nSé parte de esta jornada de innovación, sostenibilidad y conocimiento.\n\n📅 Organiza: AIME – Asociación de Ingenieros de Minas del Ecuador\n📞 Información: +593 96 820 4060\n🔗 Regístrate aquí: https://forms.gle/iXtSkrUUKFMM1Gcf6\n🌍 www.aimecuador.org",
          "media": {
            "image": {
              "height": 900,
              "src": "https://scontent-atl3-1.xx.fbcdn.net/v/t39.30808-6/596786392_875445025135309_8508033657183568428_n.jpg?stp=dst-jpg_p720x720_tt6&_nc_cat=106&ccb=1-7&_nc_sid=13d280&_nc_eui2=AeFSHtIMn5aZiB8nZfxtpCOuoCzL7zohGFKgLMvvOiEYUjLgc2ys9m3ECehMywwQOtcB6PNNg7jS0M3-IjoJ9y3D&_nc_ohc=VIuBhZhrtX8Q7kNvwH5Rmwg&_nc_oc=Adk5d3Buuzo1RFlYSs6koNDRXxFt5_hOLLAMZe5Jwncl_LmRzmx1gTjYYSUAsE1-KS0&_nc_zt=23&_nc_ht=scontent-atl3-1.xx&edm=AKIiGfEEAAAA&_nc_gid=m-7-d1tlbPvrW7UzcLK_qg&_nc_tpa=Q5bMBQErHvnQh0sdim-OBuQgfvVfOZZj_w1M6gidjEU-hibFhHrBLFux-Zm6ZpsV3InuNPOHN6xMzxTopg&oh=00_AfsGZwhFluzyfvaLrEg0qIHD79tfHM7ws2RmkCX6CWqU6Q&oe=699F9CD3",
              "width": 720
            }
          },
          "target": {
            "id": "875445021801976",
            "url": "https://www.facebook.com/photo.php?fbid=875445021801976&set=a.247201474626337&type=3"
          },
          "type": "photo",
          "url": "https://www.facebook.com/photo.php?fbid=875445021801976&set=a.247201474626337&type=3"
        }
      ]
    },
    "id": "145812602695267_875445775135234"
  },
  {
    "message": "Foro Minería 360° | 10–11 de diciembre 2025 | 18h00–20h00\nSé parte del evento que reúne tecnología, innovación y sostenibilidad para el futuro del sector minero.\n\n📲 Regístrate escaneando el código QR y participa en el sorteo de un cupo para el PIIMU 2026.\n🎓 Además, recibe tu certificado de participación.\n\n🔴 Transmisión en vivo por Facebook Live\n¡No te lo pierdas!",
    "created_time": "2025-12-08T16:05:12+0000",
    "full_picture": "https://scontent-atl3-2.xx.fbcdn.net/v/t39.30808-6/596812561_874399445239867_3539140966045703541_n.jpg?stp=dst-jpg_p720x720_tt6&_nc_cat=105&ccb=1-7&_nc_sid=13d280&_nc_eui2=AeH5HGUBEervIwiCTglXtFrg1SVviaqurpDVJW-Jqq6ukCnj_fmF-b2FVLAmT2qRPCnPiroY-zxGiNEzoE2UvpPw&_nc_ohc=VvnWz6Q-EXUQ7kNvwHgRuXy&_nc_oc=AdmTapnjH3lKKI1c83db1Yk3KMGmeanJGQ8vHR_04HPzBlbYL7q2zfEdZDJJseQwKCw&_nc_zt=23&_nc_ht=scontent-atl3-2.xx&edm=AKIiGfEEAAAA&_nc_gid=m-7-d1tlbPvrW7UzcLK_qg&_nc_tpa=Q5bMBQFspjtWmev3sBCZyLU-IfoBaZlAAcEP3UuG8mjyIPU48IFUrGT347qxknkyxuvxt2JYNf1ggEAUmw&oh=00_AfttjYV61cG1gqDpokwUnZw4YTlJ9ZCG7bkXroS3_Xfv7A&oe=699F9E7F",
    "permalink_url": "https://www.facebook.com/686939690652511/posts/874399545239857",
    "attachments": {
      "data": [
        {
          "description": "Foro Minería 360° | 10–11 de diciembre 2025 | 18h00–20h00\nSé parte del evento que reúne tecnología, innovación y sostenibilidad para el futuro del sector minero.\n\n📲 Regístrate escaneando el código QR y participa en el sorteo de un cupo para el PIIMU 2026.\n🎓 Además, recibe tu certificado de participación.\n\n🔴 Transmisión en vivo por Facebook Live\n¡No te lo pierdas!",
          "media": {
            "image": {
              "height": 900,
              "src": "https://scontent-atl3-2.xx.fbcdn.net/v/t39.30808-6/596812561_874399445239867_3539140966045703541_n.jpg?stp=dst-jpg_p720x720_tt6&_nc_cat=105&ccb=1-7&_nc_sid=13d280&_nc_eui2=AeH5HGUBEervIwiCTglXtFrg1SVviaqurpDVJW-Jqq6ukCnj_fmF-b2FVLAmT2qRPCnPiroY-zxGiNEzoE2UvpPw&_nc_ohc=VvnWz6Q-EXUQ7kNvwHgRuXy&_nc_oc=AdmTapnjH3lKKI1c83db1Yk3KMGmeanJGQ8vHR_04HPzBlbYL7q2zfEdZDJJseQwKCw&_nc_zt=23&_nc_ht=scontent-atl3-2.xx&edm=AKIiGfEEAAAA&_nc_gid=m-7-d1tlbPvrW7UzcLK_qg&_nc_tpa=Q5bMBQEC-CXPkA4tY28KTK_LBFq8ZTgwUkgvm5TCc0Q54_KnxYnkzGCqsJBneI0Zn-RJYTZB6A-NrhdrWw&oh=00_Afs1Q3Qp7aqxA_SXSkEj9eiBdtKMm2YJMDFGdKNyGmraFQ&oe=699F9E7F",
              "width": 720
            }
          },
          "target": {
            "id": "874399441906534",
            "url": "https://www.facebook.com/photo.php?fbid=874399441906534&set=a.247201474626337&type=3"
          },
          "type": "photo",
          "url": "https://www.facebook.com/photo.php?fbid=874399441906534&set=a.247201474626337&type=3"
        }
      ]
    },
    "id": "145812602695267_874399545239857"
  },
  {
    "created_time": "2025-12-08T00:13:12+0000",
    "full_picture": "https://scontent-atl3-2.xx.fbcdn.net/v/t39.30808-6/597769662_873881828624962_5375894682908564445_n.jpg?stp=c488.0.1072.1072a_dst-jpg_s720x720_tt6&_nc_cat=101&ccb=1-7&_nc_sid=b2e06f&_nc_eui2=AeFurxyhsIB_VKehs9if-F_aCqYCC7DPTT0KpgILsM9NPYkkQCkmWzg6eyx4aCEuiOMmEhNTjRMWu1iSzmlJsvLC&_nc_ohc=oJuEE89mkSAQ7kNvwGX-qbS&_nc_oc=AdkAIX2y1dGu06IFZIQndm4uk8DUKejoJTJ9jBEqU-yRRSPCdc5LQZg-SKMjWuYytTk&_nc_zt=23&_nc_ht=scontent-atl3-2.xx&edm=AKIiGfEEAAAA&_nc_gid=m-7-d1tlbPvrW7UzcLK_qg&_nc_tpa=Q5bMBQFKUNzCqol9GfHQ8ohpoiU1e5EeizSqBAtBVMcNHZ-2b5AcxJguzPca_N332qPr_W3-SYLnJfgLBA&oh=00_Afs4_TT_mLCD4e_X5Z_-NVWsJC8k6NPG22h2OaXxWAtvCQ&oe=699F7789",
    "permalink_url": "https://www.facebook.com/events/1366092061562383/",
    "attachments": {
      "data": [
        {
          "description": "35 asistieron · 20 interesados",
          "media": {
            "image": {
              "height": 720,
              "src": "https://scontent-atl3-2.xx.fbcdn.net/v/t39.30808-6/597769662_873881828624962_5375894682908564445_n.jpg?stp=c488.0.1072.1072a_dst-jpg_s720x720_tt6&_nc_cat=101&ccb=1-7&_nc_sid=b2e06f&_nc_eui2=AeFurxyhsIB_VKehs9if-F_aCqYCC7DPTT0KpgILsM9NPYkkQCkmWzg6eyx4aCEuiOMmEhNTjRMWu1iSzmlJsvLC&_nc_ohc=oJuEE89mkSAQ7kNvwGX-qbS&_nc_oc=AdkAIX2y1dGu06IFZIQndm4uk8DUKejoJTJ9jBEqU-yRRSPCdc5LQZg-SKMjWuYytTk&_nc_zt=23&_nc_ht=scontent-atl3-2.xx&edm=AKIiGfEEAAAA&_nc_gid=m-7-d1tlbPvrW7UzcLK_qg&_nc_tpa=Q5bMBQGHV-wdB_7ZmpvRqX6L0mnEXPZBxnMZN2bBH9_1zz6JdOc-CuzTa-x-vnq8KeCNECaSxItyEU-fwQ&oh=00_AftzKr--5kLuwhxZz6AKQ2MUrOv6ng8RajWyN5JTQjOs5Q&oe=699F7789",
              "width": 720
            }
          },
          "target": {
            "id": "1366092061562383",
            "url": "https://www.facebook.com/events/1366092061562383/"
          },
          "title": "FORO MINERIA 360º DIA 1",
          "type": "event",
          "url": "https://www.facebook.com/events/1366092061562383/"
        }
      ]
    },
    "id": "145812602695267_1366092061562383"
  },
  {
    "message": "AIME da la bienvenida a Gruentec Environmental Services   como auspiciante del Foro Minería 360°, el evento online que reúne a expertos, empresas y líderes del sector para compartir innovación, tecnología y nuevas tendencias que están impulsando la minería moderna.\n\n📆 10 y 11 de diciembre de 2025\n⏰ 18h00 – 20h00\n💻 Modalidad online\n\n¡Únete a esta edición y conéctate con los protagonistas del desarrollo minero en el país!\n\n👉 Regístrate aquí: https://forms.gle/iXtSkrUUKFMM1Gcf6\n\n¡Gracias, por formar parte de esta edición y apoyar el crecimiento del sector minero!",
    "created_time": "2025-12-07T21:53:15+0000",
    "full_picture": "https://scontent-atl3-3.xx.fbcdn.net/v/t39.30808-6/596551288_873818521964626_2865587830799681625_n.jpg?stp=dst-jpg_s720x720_tt6&_nc_cat=110&ccb=1-7&_nc_sid=13d280&_nc_eui2=AeESw09eVGNU2FGrYq6d96PaHcKtQzoAMxEdwq1DOgAzEexn5oOy8bW1mz9qzgMY835mP4xaj2DRx0mEny4tKBN1&_nc_ohc=Z6oZBioNJQMQ7kNvwHPevqD&_nc_oc=Adl_6v_Ro8BzKzbPoKTpWiJTLV2QNRnQlZ9WdYaZsVNcgyuATtCWy7R4VJRTJkM8wg8&_nc_zt=23&_nc_ht=scontent-atl3-3.xx&edm=AKIiGfEEAAAA&_nc_gid=m-7-d1tlbPvrW7UzcLK_qg&_nc_tpa=Q5bMBQHdx-L35e8wiUxmEym8_BM8DLx4Bu4aU2ThthFTQTOFD73IHwd_LmeJkZUCT_QY-fm5GqJfj-vMtQ&oh=00_AfvcvGqSSxyLXP9Qd27AomAVP0iME3AxXUCjPL1fS5b6Hw&oe=699F8885",
    "permalink_url": "https://www.facebook.com/686939690652511/posts/873821085297703",
    "attachments": {
      "data": [
        {
          "description": "AIME da la bienvenida a Gruentec Environmental Services   como auspiciante del Foro Minería 360°, el evento online que reúne a expertos, empresas y líderes del sector para compartir innovación, tecnología y nuevas tendencias que están impulsando la minería moderna.\n\n📆 10 y 11 de diciembre de 2025\n⏰ 18h00 – 20h00\n💻 Modalidad online\n\n¡Únete a esta edición y conéctate con los protagonistas del desarrollo minero en el país!\n\n👉 Regístrate aquí: https://forms.gle/iXtSkrUUKFMM1Gcf6\n\n¡Gracias, por formar parte de esta edición y apoyar el crecimiento del sector minero!",
          "media": {
            "image": {
              "height": 720,
              "src": "https://scontent-atl3-3.xx.fbcdn.net/v/t39.30808-6/596551288_873818521964626_2865587830799681625_n.jpg?stp=dst-jpg_s720x720_tt6&_nc_cat=110&ccb=1-7&_nc_sid=13d280&_nc_eui2=AeESw09eVGNU2FGrYq6d96PaHcKtQzoAMxEdwq1DOgAzEexn5oOy8bW1mz9qzgMY835mP4xaj2DRx0mEny4tKBN1&_nc_ohc=Z6oZBioNJQMQ7kNvwHPevqD&_nc_oc=Adl_6v_Ro8BzKzbPoKTpWiJTLV2QNRnQlZ9WdYaZsVNcgyuATtCWy7R4VJRTJkM8wg8&_nc_zt=23&_nc_ht=scontent-atl3-3.xx&edm=AKIiGfEEAAAA&_nc_gid=m-7-d1tlbPvrW7UzcLK_qg&_nc_tpa=Q5bMBQFTIOInRCVgP2s1_AShalXz8IjahAbVBDy8w3NyRcbD34QrtDUTB7u18ynRCGv1ZJlNQzr8lICEXQ&oh=00_AfukexKdipQO_VewP86J_9_GgZYe3ald6a25DYqIPvcW4w&oe=699F8885",
              "width": 720
            }
          },
          "target": {
            "id": "873818518631293",
            "url": "https://www.facebook.com/photo.php?fbid=873818518631293&set=a.247201474626337&type=3"
          },
          "type": "photo",
          "url": "https://www.facebook.com/photo.php?fbid=873818518631293&set=a.247201474626337&type=3"
        }
      ]
    },
    "id": "145812602695267_873821085297703"
  },
  {
    "message": "✨ Desde AIME celebramos la grandeza de nuestra querida Quito.\nHonramos su historia, su cultura y la fuerza de su gente.\nSigamos construyendo juntos una ciudad más innovadora, solidaria y humana.\n ¡Que viva Quito! 🎉🏙️💙",
    "created_time": "2025-12-05T22:40:55+0000",
    "full_picture": "https://scontent-atl3-2.xx.fbcdn.net/v/t39.30808-6/596000263_872320642114414_2326431462490621059_n.jpg?stp=dst-jpg_s720x720_tt6&_nc_cat=104&ccb=1-7&_nc_sid=13d280&_nc_eui2=AeEozg-1yg7uoUvfqGr01VJPewuDGfH-ctJ7C4MZ8f5y0nL_o2_TSrZroU_eWXUSVMDWy_RXn9MLFImocO8K52UF&_nc_ohc=qEwgNUsNAywQ7kNvwFXiGws&_nc_oc=AdnrvEwPC0aNQMO4YP7gfj2j1vryfIXBZeFOsnCWExhbGeSnFZ8bzPEd2NPMHWfMAzg&_nc_zt=23&_nc_ht=scontent-atl3-2.xx&edm=AKIiGfEEAAAA&_nc_gid=m-7-d1tlbPvrW7UzcLK_qg&_nc_tpa=Q5bMBQEzQcPEoFOSZsTJXtXtcDb0xiuyS5uLrw_PRoU_lZhFm4dyz_IRVvxFN5Rrj6mUCGVvstmXnx1r2w&oh=00_AfuBzFqef4q_iFrvcQn0S4uJqNzhOdPdXfjzgcTJ2QMRvw&oe=699F7708",
    "permalink_url": "https://www.facebook.com/686939690652511/posts/872321402114338",
    "attachments": {
      "data": [
        {
          "description": "✨ Desde AIME celebramos la grandeza de nuestra querida Quito.\nHonramos su historia, su cultura y la fuerza de su gente.\nSigamos construyendo juntos una ciudad más innovadora, solidaria y humana.\n ¡Que viva Quito! 🎉🏙️💙",
          "media": {
            "image": {
              "height": 720,
              "src": "https://scontent-atl3-2.xx.fbcdn.net/v/t39.30808-6/596000263_872320642114414_2326431462490621059_n.jpg?stp=dst-jpg_s720x720_tt6&_nc_cat=104&ccb=1-7&_nc_sid=13d280&_nc_eui2=AeEozg-1yg7uoUvfqGr01VJPewuDGfH-ctJ7C4MZ8f5y0nL_o2_TSrZroU_eWXUSVMDWy_RXn9MLFImocO8K52UF&_nc_ohc=qEwgNUsNAywQ7kNvwFXiGws&_nc_oc=AdnrvEwPC0aNQMO4YP7gfj2j1vryfIXBZeFOsnCWExhbGeSnFZ8bzPEd2NPMHWfMAzg&_nc_zt=23&_nc_ht=scontent-atl3-2.xx&edm=AKIiGfEEAAAA&_nc_gid=m-7-d1tlbPvrW7UzcLK_qg&_nc_tpa=Q5bMBQH7W4IrLAGJa92ruVJzCoe-73R1ZGNieJaVU_V5KzTK5U6nBf_SFm138v3bMM3qknmEjDt_iFO-3A&oh=00_Aft97fcxipjArruRO5scHJQP6OS-T1PKCB-IMwBJ4ejYEA&oe=699F7708",
              "width": 720
            }
          },
          "target": {
            "id": "872320638781081",
            "url": "https://www.facebook.com/photo.php?fbid=872320638781081&set=a.247201474626337&type=3"
          },
          "type": "photo",
          "url": "https://www.facebook.com/photo.php?fbid=872320638781081&set=a.247201474626337&type=3"
        }
      ]
    },
    "id": "145812602695267_872321402114338"
  },
  {
    "message": "AIME da la bienvenida a ISG pit to ship como auspiciante del Foro Minería 360°, el evento online que reúne a empresas, profesionales y expertos para compartir innovación, tecnología y nuevas tendencias que impulsan el desarrollo del sector minero.\n\n📆 10 y 11 de diciembre de 2025\n⏰ 18h00 – 20h00\n💻 Modalidad online\n\n¡Sé parte de esta edición y conéctate con los actores clave que están transformando la minería en el país!\n\n👉 Regístrate aquí: https://forms.gle/iXtSkrUUKFMM1Gcf6\n\n¡Gracias, ISG, por unirse a esta iniciativa y contribuir al fortalecimiento del sector minero!",
    "created_time": "2025-12-04T23:47:02+0000",
    "full_picture": "https://scontent-atl3-3.xx.fbcdn.net/v/t39.30808-6/593892397_871572692189209_8549889311072678052_n.jpg?stp=dst-jpg_s720x720_tt6&_nc_cat=109&ccb=1-7&_nc_sid=13d280&_nc_eui2=AeEH7_Zo6xRaVW4VyFPkLRA8V7B45P2YJgdXsHjk_ZgmB3r3a_3I_gvV28iUagnhrEdIFOyUxxfBpZv7hBjlD9_L&_nc_ohc=S3CDzWwUELEQ7kNvwHDLpbg&_nc_oc=AdmgvmhVBEe-ZLld-hKnoDWWB585V_UOsSmMLnbxE0BqDoL2nek5EneuyrBF-TIoLCM&_nc_zt=23&_nc_ht=scontent-atl3-3.xx&edm=AKIiGfEEAAAA&_nc_gid=m-7-d1tlbPvrW7UzcLK_qg&_nc_tpa=Q5bMBQEw9iP5uzkvGNNutbDcfsG0da3ziWloc7_MHyDIbjqTMJInDGe-oCsful3-jGcyE3LvGFYOB0Natw&oh=00_AfsRwlbXsRzOq1dT76lSflykI78k89XwqBKWFmtAoT8fJA&oe=699FA3A2",
    "permalink_url": "https://www.facebook.com/686939690652511/posts/871575912188887",
    "attachments": {
      "data": [
        {
          "description": "AIME da la bienvenida a ISG pit to ship como auspiciante del Foro Minería 360°, el evento online que reúne a empresas, profesionales y expertos para compartir innovación, tecnología y nuevas tendencias que impulsan el desarrollo del sector minero.\n\n📆 10 y 11 de diciembre de 2025\n⏰ 18h00 – 20h00\n💻 Modalidad online\n\n¡Sé parte de esta edición y conéctate con los actores clave que están transformando la minería en el país!\n\n👉 Regístrate aquí: https://forms.gle/iXtSkrUUKFMM1Gcf6\n\n¡Gracias, ISG, por unirse a esta iniciativa y contribuir al fortalecimiento del sector minero!",
          "media": {
            "image": {
              "height": 720,
              "src": "https://scontent-atl3-3.xx.fbcdn.net/v/t39.30808-6/593892397_871572692189209_8549889311072678052_n.jpg?stp=dst-jpg_s720x720_tt6&_nc_cat=109&ccb=1-7&_nc_sid=13d280&_nc_eui2=AeEH7_Zo6xRaVW4VyFPkLRA8V7B45P2YJgdXsHjk_ZgmB3r3a_3I_gvV28iUagnhrEdIFOyUxxfBpZv7hBjlD9_L&_nc_ohc=S3CDzWwUELEQ7kNvwHDLpbg&_nc_oc=AdmgvmhVBEe-ZLld-hKnoDWWB585V_UOsSmMLnbxE0BqDoL2nek5EneuyrBF-TIoLCM&_nc_zt=23&_nc_ht=scontent-atl3-3.xx&edm=AKIiGfEEAAAA&_nc_gid=m-7-d1tlbPvrW7UzcLK_qg&_nc_tpa=Q5bMBQHTZ-pWdhcx9cG2ffBINhFc_WR1owXptfRh6_QVJzMYHzR0q7cDqP6jTIJwD_l0g1YAjanJPTblXQ&oh=00_AfuEyaYgcQs4FSEt2wRT5I0rcHv04rvYsAQzJWIGI03Kfw&oe=699FA3A2",
              "width": 720
            }
          },
          "target": {
            "id": "871572688855876",
            "url": "https://www.facebook.com/photo.php?fbid=871572688855876&set=a.247201474626337&type=3"
          },
          "type": "photo",
          "url": "https://www.facebook.com/photo.php?fbid=871572688855876&set=a.247201474626337&type=3"
        }
      ]
    },
    "id": "145812602695267_871575912188887"
  },
  {
    "message": "Acompañamos a Michael y Margaret Gibbons Parra por la pérdida de su padre, Sr.Patrick Gibbons.\nExtendemos nuestras condolencias y nuestro apoyo en este momento difícil.\nDescanse en paz.",
    "created_time": "2025-12-04T16:28:09+0000",
    "full_picture": "https://scontent-atl3-3.xx.fbcdn.net/v/t39.30808-6/594057930_871348675544944_1057878925621979726_n.jpg?stp=dst-jpg_s720x720_tt6&_nc_cat=111&ccb=1-7&_nc_sid=13d280&_nc_eui2=AeGZt9cogVGW1S7rPuRov1Aqagf0cw98oQRqB_RzD3yhBPsE4vKBdug8klHm-q7y1zp1sSaGwOuCRkUqv0qqmXAn&_nc_ohc=_wskjK_Fzu8Q7kNvwHkldSb&_nc_oc=AdnPO4HO9TCtcjVKSNjrxZMTK8POVh7iIz3a0c9lAJfeY_eV8-vssVuyGeJ9liZR2J8&_nc_zt=23&_nc_ht=scontent-atl3-3.xx&edm=AKIiGfEEAAAA&_nc_gid=m-7-d1tlbPvrW7UzcLK_qg&_nc_tpa=Q5bMBQFSBWvWGRx-hzoGWBHrh7xNVfn_hI-aGaeB_x7Y-NtxeRRPxmX7nCUmkjnEY3fsBUPykv9GJVnPRA&oh=00_AftXM5jbNU1AQ9S61us6enIM9Dp5px03pGDaJxw4CHW1jA&oe=699F96E1",
    "permalink_url": "https://www.facebook.com/686939690652511/posts/871348748878270",
    "attachments": {
      "data": [
        {
          "description": "Acompañamos a Michael y Margaret Gibbons Parra por la pérdida de su padre, Sr.Patrick Gibbons.\nExtendemos nuestras condolencias y nuestro apoyo en este momento difícil.\nDescanse en paz.",
          "media": {
            "image": {
              "height": 720,
              "src": "https://scontent-atl3-3.xx.fbcdn.net/v/t39.30808-6/594057930_871348675544944_1057878925621979726_n.jpg?stp=dst-jpg_s720x720_tt6&_nc_cat=111&ccb=1-7&_nc_sid=13d280&_nc_eui2=AeGZt9cogVGW1S7rPuRov1Aqagf0cw98oQRqB_RzD3yhBPsE4vKBdug8klHm-q7y1zp1sSaGwOuCRkUqv0qqmXAn&_nc_ohc=_wskjK_Fzu8Q7kNvwHkldSb&_nc_oc=AdnPO4HO9TCtcjVKSNjrxZMTK8POVh7iIz3a0c9lAJfeY_eV8-vssVuyGeJ9liZR2J8&_nc_zt=23&_nc_ht=scontent-atl3-3.xx&edm=AKIiGfEEAAAA&_nc_gid=m-7-d1tlbPvrW7UzcLK_qg&_nc_tpa=Q5bMBQF6Fl4FG8BKysPlwHgl2nD_OXfxp1i8VhHIjAKgGqRK-tKjdOHSuHTfP3Zt1KKNCb5K6nOVDDo24Q&oh=00_Aft79RmgbkAs66aOv9IjypwCdnhCy5u8kyM185Zlizqdag&oe=699F96E1",
              "width": 720
            }
          },
          "target": {
            "id": "871348672211611",
            "url": "https://www.facebook.com/photo.php?fbid=871348672211611&set=a.247201474626337&type=3"
          },
          "type": "photo",
          "url": "https://www.facebook.com/photo.php?fbid=871348672211611&set=a.247201474626337&type=3"
        }
      ]
    },
    "id": "145812602695267_871348748878270"
  },
  {
    "message": "“La minería ecuatoriana necesita visión, liderazgo y diálogo.\nAndrés Ycaza Palacios, Vicepresidente del Directorio de la Cámara de Minería del Ecuador, se suma al FORO MINERÍA 360° para compartir su perspectiva sobre los retos y oportunidades que marcarán el futuro del sector.”\n\n📆 10 y 11 de diciembre de 2025\n⏰ 18h00 – 20h00\n💻 Modalidad online\n🔥 ¡Regístrate hoy y participa en sorteo de un cupo para nuestro programa de intercambio PIIMU 2026.\nhttps://forms.gle/iXtSkrUUKFMM1Gcf6\n🌐 Sé parte del encuentro que impulsa una mirada integral, transparente y sostenible de la minería en el Ecuador.",
    "created_time": "2025-12-04T16:17:14+0000",
    "full_picture": "https://scontent-atl3-3.xx.fbcdn.net/v/t15.5256-10/595693210_1344384624154811_750040477068080587_n.jpg?_nc_cat=108&ccb=1-7&_nc_sid=d2b52d&_nc_eui2=AeFaBEK7qXftV8LC3ZJ1aTTfo8bSo2kMI_qjxtKjaQwj-r39gycTWNiuMcrIuPAGU_yAqQemb3BGFEWwuO8Byu4j&_nc_ohc=96tOURRlWhsQ7kNvwE8Rdax&_nc_oc=AdnolURqFDSwsLqEaB9V-MDihIK_oP7QaisrAPmP4bU_KSo-0Lw_bkU01EwRj0UIf_Q&_nc_zt=23&_nc_ht=scontent-atl3-3.xx&edm=AKIiGfEEAAAA&_nc_gid=m-7-d1tlbPvrW7UzcLK_qg&_nc_tpa=Q5bMBQFkXivxPYnmQtqNQwkxZYnztAcyf1rfEnKz_DffPWzmrDG9ClacJkuMp0TxN7RuNG0Hxbn71P5myw&oh=00_AfsIouoM83Mu-H-wPP99XTKAW9WE8yLUBClEt2Awa1QOPQ&oe=699FA7AF",
    "permalink_url": "https://www.facebook.com/reel/1375215280643296/",
    "attachments": {
      "data": [
        {
          "media": {
            "image": {
              "height": 720,
              "src": "https://scontent-atl3-3.xx.fbcdn.net/v/t15.5256-10/595693210_1344384624154811_750040477068080587_n.jpg?stp=dst-jpg_s720x720_tt6&_nc_cat=108&ccb=1-7&_nc_sid=d2b52d&_nc_eui2=AeFaBEK7qXftV8LC3ZJ1aTTfo8bSo2kMI_qjxtKjaQwj-r39gycTWNiuMcrIuPAGU_yAqQemb3BGFEWwuO8Byu4j&_nc_ohc=96tOURRlWhsQ7kNvwE8Rdax&_nc_oc=AdnolURqFDSwsLqEaB9V-MDihIK_oP7QaisrAPmP4bU_KSo-0Lw_bkU01EwRj0UIf_Q&_nc_zt=23&_nc_ht=scontent-atl3-3.xx&edm=AKIiGfEEAAAA&_nc_gid=m-7-d1tlbPvrW7UzcLK_qg&_nc_tpa=Q5bMBQHLO6gKqcDs5ZhU7a9baMI2qBiXOkmH3okJp4VcR_SZiezMbTPIdgfWlaJv8-_FMVIYi58Pd-6mcg&oh=00_AfuNJDWhHKdRe43hHPbOHjVcRQlvBL6mOcuwibpro-zVAg&oe=699FA7AF",
              "width": 405
            },
            "source": "https://video-atl3-2.xx.fbcdn.net/o1/v/t2/f2/m412/AQMUNqHO0WL-u8mRmLLj2OGl8O4XzKYaSlPXrwtS4EaGqJYCXBAkQWnWZDMz39aC2YvBoBsNkYOWov3DDb3FgenRTeSn5XXjQUhnaU4wLw.mp4?_nc_cat=101&_nc_sid=5e9851&_nc_ht=video-atl3-2.xx.fbcdn.net&_nc_ohc=VVcaCvoLSeYQ7kNvwHFBE9G&efg=eyJ2ZW5jb2RlX3RhZyI6Inhwdl9wcm9ncmVzc2l2ZS5GQUNFQk9PSy4uQzMuMzYwLnN2ZV9zZCIsInhwdl9hc3NldF9pZCI6MTM5ODE3NzMxNTI1NzI1NiwiYXNzZXRfYWdlX2RheXMiOjc4LCJ2aV91c2VjYXNlX2lkIjoxMDEyMiwiZHVyYXRpb25fcyI6NTAsInVybGdlbl9zb3VyY2UiOiJ3d3cifQ%3D%3D&ccb=17-1&vs=b97e7734ee555015&_nc_vs=HBkcFQIYQmZiX3Blcm1hbmVudC9ENDQ2QkEyM0I3NzQzRTgzMEJDODJFQzA1N0Q0RjU5Ql9tdF8wX3Byb2dyZXNzaXZlLm1wNBUAAsgBEgAoABgAGwKIB3VzZV9vaWwBMRJwcm9ncmVzc2l2ZV9yZWNpcGUBMRUAACbQ7qvj0Oj7BBUCKAJDMywXQEkLAgxJul4YBnN2ZV9zZBEAdQJllJ4BAA&_nc_gid=m-7-d1tlbPvrW7UzcLK_qg&edm=AKIiGfEEAAAA&_nc_zt=28&_nc_eui2=AeEI133kRP4Hm5P8hBDgra9pii8HsV447jmKLwexXjjuOTLRos765xdzBCLuXG_YFDs_ZI72BW8OLEHNRr24clp8&_nc_tpa=Q5bMBQES1KJ6gWVvx8TEEqnIUNKEeb_4LQS8UhSsG1dQsBUIuOAXs2wLmiFVijyM9_N-oqgSQfGLIgY7Uw&oh=00_Afs28IGCUxZjIOAEqoMhcGM2kkRRIDgEGCyWNHuIMteDWQ&oe=699F9D21&bitrate=0&tag=sve_sd"
          },
          "target": {
            "id": "1375215280643296",
            "url": "https://www.facebook.com/reel/1375215280643296/"
          },
          "type": "video_inline",
          "url": "https://www.facebook.com/reel/1375215280643296/"
        }
      ]
    },
    "id": "145812602695267_871342498878895"
  },
  {
    "message": "AIME da la bienvenida a Geocamb  Geología, Construcción, Ambiente  como auspiciante del Foro Minería 360°, el evento online que reúne a profesionales, empresas y expertos para compartir innovación, tecnología y nuevas perspectivas para el desarrollo minero.\n\n📆 10 y 11 de diciembre de 2025\n⏰ 18h00 – 20h00\n💻 Modalidad online\n\n¡Participa en esta edición y conecta con quienes están impulsando el futuro de la minería en el país!\n\n👉 Regístrate aquí: https://forms.gle/fh3YC6M15W1WWQRy6\n\n¡Gracias, GEOCAMB, por unirse a este espacio y apoyar el crecimiento del sector minero!",
    "created_time": "2025-12-03T22:00:19+0000",
    "full_picture": "https://scontent-atl3-1.xx.fbcdn.net/v/t39.30808-6/593992846_870716658941479_860062022779210705_n.jpg?stp=dst-jpg_s720x720_tt6&_nc_cat=103&ccb=1-7&_nc_sid=13d280&_nc_eui2=AeHYkF4BrqZXU987vF-WdRRYuviXHE434de6-JccTjfh15nx2r8XQq6nEX3p85kWN6e35esSt3Cj8Rzp9FFO4Q-F&_nc_ohc=6dxAkCvYu2cQ7kNvwFUY5Px&_nc_oc=AdmOZGQf9Y2HaAQbzs1TKHhzFFe_HKqA_bknBvkuyzrOwf7cyB2lRIHiywgdHDgFIcM&_nc_zt=23&_nc_ht=scontent-atl3-1.xx&edm=AKIiGfEEAAAA&_nc_gid=m-7-d1tlbPvrW7UzcLK_qg&_nc_tpa=Q5bMBQH1ogbQczNfLzM-VXx7bgr6LmQwsCWaf20STCX1YsmtmjtzvrIeHT8a_Y3yT48ZlCwGe7TcfHkcHQ&oh=00_AftyXVJ9QEVTvhrclfqXPfn2Wu4SgeUhtYhVEp38MZTLng&oe=699F85F3",
    "permalink_url": "https://www.facebook.com/686939690652511/posts/870732265606585",
    "attachments": {
      "data": [
        {
          "description": "AIME da la bienvenida a Geocamb  Geología, Construcción, Ambiente  como auspiciante del Foro Minería 360°, el evento online que reúne a profesionales, empresas y expertos para compartir innovación, tecnología y nuevas perspectivas para el desarrollo minero.\n\n📆 10 y 11 de diciembre de 2025\n⏰ 18h00 – 20h00\n💻 Modalidad online\n\n¡Participa en esta edición y conecta con quienes están impulsando el futuro de la minería en el país!\n\n👉 Regístrate aquí: https://forms.gle/fh3YC6M15W1WWQRy6\n\n¡Gracias, GEOCAMB, por unirse a este espacio y apoyar el crecimiento del sector minero!",
          "description_tags": [
            {
              "id": "32632985679649363",
              "length": 41,
              "name": "Geocamb  Geología, Construcción, Ambiente",
              "offset": 24,
              "type": "user"
            }
          ],
          "media": {
            "image": {
              "height": 720,
              "src": "https://scontent-atl3-1.xx.fbcdn.net/v/t39.30808-6/593992846_870716658941479_860062022779210705_n.jpg?stp=dst-jpg_s720x720_tt6&_nc_cat=103&ccb=1-7&_nc_sid=13d280&_nc_eui2=AeHYkF4BrqZXU987vF-WdRRYuviXHE434de6-JccTjfh15nx2r8XQq6nEX3p85kWN6e35esSt3Cj8Rzp9FFO4Q-F&_nc_ohc=6dxAkCvYu2cQ7kNvwFUY5Px&_nc_oc=AdmOZGQf9Y2HaAQbzs1TKHhzFFe_HKqA_bknBvkuyzrOwf7cyB2lRIHiywgdHDgFIcM&_nc_zt=23&_nc_ht=scontent-atl3-1.xx&edm=AKIiGfEEAAAA&_nc_gid=m-7-d1tlbPvrW7UzcLK_qg&_nc_tpa=Q5bMBQHVKqWMoUvppLt8DNB4zWTd50Gwxcrqf1YsmV-TiS8uzlwgAAH_8P17TlHWW73kEy2h6QcSrUzOfQ&oh=00_Afs2g-LR1VwNcJ4Z5EvjnsZKvPQ3ewnqtNqo604QBGgjvQ&oe=699F85F3",
              "width": 720
            }
          },
          "target": {
            "id": "870732248939920",
            "url": "https://www.facebook.com/photo.php?fbid=870732248939920&set=a.247201474626337&type=3"
          },
          "type": "photo",
          "url": "https://www.facebook.com/photo.php?fbid=870732248939920&set=a.247201474626337&type=3"
        }
      ]
    },
    "id": "145812602695267_870732265606585"
  },
  {
    "message": "El FORO MINERÍA 360° se acerca, y voces como la de Vicente Encalada ya forman parte de esta conversación clave para el futuro del sector. 🔍⚙️\n📆 10 y 11 de diciembre de 2025\n⏰ 18h00 – 20h00\n💻 Online\n🔥 ¡Regístrate hoy y participa en el evento que impulsa la minería hacia un nuevo horizonte!\nhttps://forms.gle/iXtSkrUUKFMM1Gcf6",
    "created_time": "2025-12-03T20:55:30+0000",
    "full_picture": "https://scontent-atl3-3.xx.fbcdn.net/v/t15.5256-10/593546589_771839975865167_5894713800781622036_n.jpg?_nc_cat=110&ccb=1-7&_nc_sid=d2b52d&_nc_eui2=AeG7H-1VicKMlSsVGsbJZNmaapfUCExNB8Nql9QITE0Hw4NAIkhYohhlCHtRamqhu-7Ta3UhPWtOh32zMk8Kylzw&_nc_ohc=YfalMi-F7LQQ7kNvwFzmrff&_nc_oc=Adn6N_VqxIJ2WXe2n36EoBB7iR7Tm6PTcjlt4xMZ4jOdGmaxi_09sAesn1T4xayesGA&_nc_zt=23&_nc_ht=scontent-atl3-3.xx&edm=AKIiGfEEAAAA&_nc_gid=m-7-d1tlbPvrW7UzcLK_qg&_nc_tpa=Q5bMBQEcz2yBHB8_XIP8woDxN0W565M7qF6-YuyzUDNStpLYdbnU8j1ar7y1NUZPV48jBXRldV9wGqDGag&oh=00_Aft04EBu_cY6lMAaPdJVFlZ2i4mk6IAI5RYyQh1CTpOsEg&oe=699F8C61",
    "permalink_url": "https://www.facebook.com/reel/881416474448273/",
    "attachments": {
      "data": [
        {
          "media": {
            "image": {
              "height": 720,
              "src": "https://scontent-atl3-3.xx.fbcdn.net/v/t15.5256-10/593546589_771839975865167_5894713800781622036_n.jpg?stp=dst-jpg_s720x720_tt6&_nc_cat=110&ccb=1-7&_nc_sid=d2b52d&_nc_eui2=AeG7H-1VicKMlSsVGsbJZNmaapfUCExNB8Nql9QITE0Hw4NAIkhYohhlCHtRamqhu-7Ta3UhPWtOh32zMk8Kylzw&_nc_ohc=YfalMi-F7LQQ7kNvwFzmrff&_nc_oc=Adn6N_VqxIJ2WXe2n36EoBB7iR7Tm6PTcjlt4xMZ4jOdGmaxi_09sAesn1T4xayesGA&_nc_zt=23&_nc_ht=scontent-atl3-3.xx&edm=AKIiGfEEAAAA&_nc_gid=m-7-d1tlbPvrW7UzcLK_qg&_nc_tpa=Q5bMBQFjYgSDa13ayD6dMmioeT5G3p79RRzmjM89ibv6qfsevyUrD0npxbU91-jFZ6AE-482_7zMVbh_kA&oh=00_AfuYM5ZMBAwB8mctUpbzopowVlDdf6Vhc3OYfFfQ7ZmS9g&oe=699F8C61",
              "width": 405
            },
            "source": "https://video-atl3-3.xx.fbcdn.net/o1/v/t2/f2/m412/AQONGWX43aZg1iwdoonjEK4NDZSyWvdvzSDcPdHfMDQw53Netv0XkMO-HsmpvFHH0gRAARRCjyHJlvFFD8cUswy-huuItJZ2TXXNxDPGPQ.mp4?_nc_cat=108&_nc_sid=5e9851&_nc_ht=video-atl3-3.xx.fbcdn.net&_nc_ohc=baCYCouEl0UQ7kNvwHymdbh&efg=eyJ2ZW5jb2RlX3RhZyI6Inhwdl9wcm9ncmVzc2l2ZS5GQUNFQk9PSy4uQzMuMzYwLnN2ZV9zZCIsInhwdl9hc3NldF9pZCI6NzI5Nzg4ODkyOTI0MjI2LCJhc3NldF9hZ2VfZGF5cyI6NzksInZpX3VzZWNhc2VfaWQiOjEwMTIyLCJkdXJhdGlvbl9zIjo1NCwidXJsZ2VuX3NvdXJjZSI6Ind3dyJ9&ccb=17-1&vs=766f8e856bd33603&_nc_vs=HBkcFQIYQmZiX3Blcm1hbmVudC8yQjQwQ0M3Qzk3NEY4N0UzOTBDM0NGNDhFQzRCNEM4Q19tdF8wX3Byb2dyZXNzaXZlLm1wNBUAAsgBEgAoABgAGwKIB3VzZV9vaWwBMRJwcm9ncmVzc2l2ZV9yZWNpcGUBMRUAACaEpcr7pu_LAhUCKAJDMywXQEtsSbpeNT8YBnN2ZV9zZBEAdQJllJ4BAA&_nc_gid=m-7-d1tlbPvrW7UzcLK_qg&edm=AKIiGfEEAAAA&_nc_zt=28&_nc_eui2=AeGbNNhJDjrK2VXMC6QxUMSymarbKBtvrEKZqtsoG2-sQhcvCINM0rDBZ02PIbjR7zVNvWXGtxX_0siLZy4bL1a6&_nc_tpa=Q5bMBQF-impCp8hmX55P0kbhPbyQVzedU4PquA9ZddITKEa5T0-pyDqnAtQI_hMM70XvI4UyUxvH6Z496w&oh=00_AfsuIasEqtnUxnbRUXKgULGseX0X63MO7y8msv7ou_hsrw&oe=699F8002&bitrate=0&tag=sve_sd"
          },
          "target": {
            "id": "881416474448273",
            "url": "https://www.facebook.com/reel/881416474448273/"
          },
          "type": "video_inline",
          "url": "https://www.facebook.com/reel/881416474448273/"
        }
      ]
    },
    "id": "145812602695267_870704288942716"
  },
  {
    "message": "AIME da la bienvenida a Kluane Drilling LTD. como auspiciante del Foro Minería 360°, un evento online que reúne a los líderes y especialistas del sector para explorar innovación, tecnología y nuevas perspectivas para la minería.\n\n📆 10 y 11 de diciembre de 2025\n⏰ 18h00 – 20h00\n💻 Modalidad online\n\n¡Sé parte de esta edición y conecta con las empresas y expertos que están impulsando el futuro de la industria!\n\n👉 Regístrate aquí: [Enlace de registro]\n\n¡Gracias, Kluane Drilling LTD.Kluane Drilling LTD., por unirse a esta iniciativa y apoyar el desarrollo minero del país!",
    "created_time": "2025-12-02T23:44:08+0000",
    "full_picture": "https://scontent-atl3-3.xx.fbcdn.net/v/t39.30808-6/593883661_870024545677357_5736797275463398112_n.jpg?stp=dst-jpg_s720x720_tt6&_nc_cat=108&ccb=1-7&_nc_sid=13d280&_nc_eui2=AeE8xcB9IZf4L99XQUq0fU5qPz4Uee34DA8_PhR57fgMD7rd4fQG-0LHpSWvMbUzBU-flB0iscWziMQNVTULpncW&_nc_ohc=sb-sXS9OiLMQ7kNvwGAlBdW&_nc_oc=Adn5HPV0DcdieemBy02E2BuokRRwBMT0ZhXi1F_yvbJF55UXYzfC-pRa_fbDjXP-D5s&_nc_zt=23&_nc_ht=scontent-atl3-3.xx&edm=AKIiGfEEAAAA&_nc_gid=m-7-d1tlbPvrW7UzcLK_qg&_nc_tpa=Q5bMBQHRmb9QVrwjJqvKOrWRrE6DOeDC34sGiYTVYk4VaJSqXVGYJUjbK62utr8ZiM3Fvw1oS6SuciHq7g&oh=00_AftktbfNaQ77Erz85O3ddbGVi1nbn03Xeznoo7747obEXw&oe=699F9919",
    "permalink_url": "https://www.facebook.com/686939690652511/posts/870041555675656",
    "attachments": {
      "data": [
        {
          "description": "AIME da la bienvenida a Kluane Drilling LTD. como auspiciante del Foro Minería 360°, un evento online que reúne a los líderes y especialistas del sector para explorar innovación, tecnología y nuevas perspectivas para la minería.\n\n📆 10 y 11 de diciembre de 2025\n⏰ 18h00 – 20h00\n💻 Modalidad online\n\n¡Sé parte de esta edición y conecta con las empresas y expertos que están impulsando el futuro de la industria!\n\n👉 Regístrate aquí: [Enlace de registro]\n\n¡Gracias, Kluane Drilling LTD.Kluane Drilling LTD., por unirse a esta iniciativa y apoyar el desarrollo minero del país!",
          "description_tags": [
            {
              "id": "24380445694917586",
              "length": 20,
              "name": "Kluane Drilling LTD.",
              "offset": 461,
              "type": "user"
            },
            {
              "id": "24380445694917586",
              "length": 20,
              "name": "Kluane Drilling LTD.",
              "offset": 481,
              "type": "user"
            }
          ],
          "media": {
            "image": {
              "height": 720,
              "src": "https://scontent-atl3-3.xx.fbcdn.net/v/t39.30808-6/593883661_870024545677357_5736797275463398112_n.jpg?stp=dst-jpg_s720x720_tt6&_nc_cat=108&ccb=1-7&_nc_sid=13d280&_nc_eui2=AeE8xcB9IZf4L99XQUq0fU5qPz4Uee34DA8_PhR57fgMD7rd4fQG-0LHpSWvMbUzBU-flB0iscWziMQNVTULpncW&_nc_ohc=sb-sXS9OiLMQ7kNvwGAlBdW&_nc_oc=Adn5HPV0DcdieemBy02E2BuokRRwBMT0ZhXi1F_yvbJF55UXYzfC-pRa_fbDjXP-D5s&_nc_zt=23&_nc_ht=scontent-atl3-3.xx&edm=AKIiGfEEAAAA&_nc_gid=m-7-d1tlbPvrW7UzcLK_qg&_nc_tpa=Q5bMBQFDzSp5Hns1sDclKQB9ivDwBG9XQkeibj6pMqcFuUu3UFktA5HpJU3jgm1cQxvhbhXrtmMwd6i9cQ&oh=00_AfvOGjs_UMs6EDbURkjW4NqlN2TVpRnqP5ThkXlzGyGKXQ&oe=699F9919",
              "width": 720
            }
          },
          "target": {
            "id": "870094662337012",
            "url": "https://www.facebook.com/photo.php?fbid=870094662337012&set=a.247201474626337&type=3"
          },
          "type": "photo",
          "url": "https://www.facebook.com/photo.php?fbid=870094662337012&set=a.247201474626337&type=3"
        }
      ]
    },
    "id": "145812602695267_870041555675656"
  },
  {
    "message": "AIME da la bienvenida a SolGold Ecuador  como auspiciante del Foro Minería 360°, un espacio online donde la industria minera se conecta con la innovación, la tecnología y las nuevas oportunidades de crecimiento.\n\n📆 10 y 11 de diciembre de 2025\n⏰ 18h00 – 20h00\n💻 Modalidad online\n\n¡Únete a este evento que reúne a los protagonistas del sector y descubre las tendencias que están transformando la minería!\n\n👉 Regístrate aquí:https://docs.google.com/forms/d/e/1FAIpQLScEgLNlJYjYd427tmNCnOOSNuGR4wE34Ic-dl7MBRRPONTARg/viewform\n\n¡Gracias, SolGold Ecuador  , por ser parte de esta edición y potenciar el desarrollo minero del país!",
    "created_time": "2025-12-01T16:55:07+0000",
    "full_picture": "https://scontent-atl3-1.xx.fbcdn.net/v/t39.30808-6/593758439_869097005770111_1102481706187445314_n.jpg?stp=dst-jpg_s720x720_tt6&_nc_cat=106&ccb=1-7&_nc_sid=13d280&_nc_eui2=AeE1Ldg1ECAWm1jwOxojzMff960TW7TYuJH3rRNbtNi4kebYC-Wd7wuW9EloHxqOTVg8UL7ZJcaFF7PBEhSUDfUN&_nc_ohc=v1s_RaELnkUQ7kNvwE7bp3k&_nc_oc=AdnvvziyUNQ6aSYI-Org_lnkpom7T7oriJFQbOajzUYK6hKtXn-FcrWFbhAcnh2NayA&_nc_zt=23&_nc_ht=scontent-atl3-1.xx&edm=AKIiGfEEAAAA&_nc_gid=m-7-d1tlbPvrW7UzcLK_qg&_nc_tpa=Q5bMBQFlJkTUanP8JKKmTsyOU0TZkZlKqBQDwlTBCMKFhqiS5vGTf4nXqVAIgmKNNpKh16Q28YekWIhIhg&oh=00_AfvpyK-kWks2eNe5G8e7myh1IR5Nn7LD3hit_4d6mzxdhA&oe=699F83CA",
    "permalink_url": "https://www.facebook.com/686939690652511/posts/869103609102784",
    "attachments": {
      "data": [
        {
          "description": "AIME da la bienvenida a SolGold Ecuador  como auspiciante del Foro Minería 360°, un espacio online donde la industria minera se conecta con la innovación, la tecnología y las nuevas oportunidades de crecimiento.\n\n📆 10 y 11 de diciembre de 2025\n⏰ 18h00 – 20h00\n💻 Modalidad online\n\n¡Únete a este evento que reúne a los protagonistas del sector y descubre las tendencias que están transformando la minería!\n\n👉 Regístrate aquí:https://docs.google.com/forms/d/e/1FAIpQLScEgLNlJYjYd427tmNCnOOSNuGR4wE34Ic-dl7MBRRPONTARg/viewform\n\n¡Gracias, SolGold Ecuador  , por ser parte de esta edición y potenciar el desarrollo minero del país!",
          "description_tags": [
            {
              "id": "24348207891500159",
              "length": 15,
              "name": "SolGold Ecuador",
              "offset": 24,
              "type": "user"
            },
            {
              "id": "24348207891500159",
              "length": 15,
              "name": "SolGold Ecuador",
              "offset": 534,
              "type": "user"
            }
          ],
          "media": {
            "image": {
              "height": 720,
              "src": "https://scontent-atl3-1.xx.fbcdn.net/v/t39.30808-6/593758439_869097005770111_1102481706187445314_n.jpg?stp=dst-jpg_s720x720_tt6&_nc_cat=106&ccb=1-7&_nc_sid=13d280&_nc_eui2=AeE1Ldg1ECAWm1jwOxojzMff960TW7TYuJH3rRNbtNi4kebYC-Wd7wuW9EloHxqOTVg8UL7ZJcaFF7PBEhSUDfUN&_nc_ohc=v1s_RaELnkUQ7kNvwE7bp3k&_nc_oc=AdnvvziyUNQ6aSYI-Org_lnkpom7T7oriJFQbOajzUYK6hKtXn-FcrWFbhAcnh2NayA&_nc_zt=23&_nc_ht=scontent-atl3-1.xx&edm=AKIiGfEEAAAA&_nc_gid=m-7-d1tlbPvrW7UzcLK_qg&_nc_tpa=Q5bMBQEqyhg18EzUzrS-myTgmd3Dpn48jeWHjhh5HgiMlvoej5ucd9jNickf5yxTaEyrHsjuDADvXRsitQ&oh=00_AfteWZXLN-RQl0LMI_2VstjbsWpDS94berb9mbbrW4kpnw&oe=699F83CA",
              "width": 719
            }
          },
          "target": {
            "id": "869097002436778",
            "url": "https://www.facebook.com/photo.php?fbid=869097002436778&set=a.247201474626337&type=3"
          },
          "type": "photo",
          "url": "https://www.facebook.com/photo.php?fbid=869097002436778&set=a.247201474626337&type=3"
        }
      ]
    },
    "id": "145812602695267_869103609102784"
  }
]